probador.v
`timescale 1ns/1ns // escala de tiempo

/*Probador del registro de cuatro
   bits*/
module tester (
    output reg CLK,
    output reg ENB,
    output reg [1:0] MODO,
    output reg [3:0] D,
    input [3:0] Q,
    input RCO
);

/*Creacion del reloj, en este apartado de codigo se inicializa el reloj
donde este cambia cada segundo de tiempo, siendo 0 en uno y 1 en otro
y asi hasta terminar de correr las pruebas*/

always begin
    CLK = 1'b0; #1;
    CLK = 1'b1; #1;
end

// Ejecucion de pruebas

/*initial begin
    $display("Prueba #1: Cuenta ascendente");
    $display("ENB    MODO   D        Q       RCO");

    //primera instruccion 
    ENB = 1'b1; //activo el enable por que quiero que este empieza a cambiar
    MODO = 2'b11;
    D[3:0] = 4'b0000;

    //segunda y tercera instruccion
    /*Con esta se pretende enviar el flanco activo en CLK
    y establecer el MODO igual a  2'b00*/
    //#1; #1;
    //MODO = 2'b00; // Esta en 0000 para iniciar

    // se envian 16 flancos de reloj
    /*Para este caso es muy importante que tomemos en cuenta que el RCO no sera
    igual a 1, hasta que a 1111 no se le sume 1, en este caso ya tomaria el llevo
    y RCO = 1 */
    /*#1; #1;
    #1; #1;
    #1; #1;
    #1; #1;
    #1; #1;
    #1; #1;
    #1; #1;
    #1; #1;
    #1; #1;
    #1; #1;
    #1; #1;
    #1; #1;
    #1; #1;
    #1; #1;
    #1; #1;
    #1; #1; 
    #1; #1; //aqui ya muestra el llevo 

    $display("\nPrueba #2: Cuenta descendente");
    $display("ENB   MODO   D        Q       RCO");

    //primera instruccion 
    ENB = 1'b1; //activo el enable por que quiero que este empieza a cambiar
    MODO = 2'b11;
    D[3:0] = 4'b1111; //Inicio en 1111

    //segunda y tercera instruccion
    /*Con esta se pretende enviar el flanco activo en CLK
    y establecer el MODO igual a  2'b00*/
    //#1; #1;
    //MODO = 2'b01; // Esta en 0000 para iniciar

    // se envian 16 flancos de reloj
    /*#1; #1;
    #1; #1;
    #1; #1;
    #1; #1;
    #1; #1;
    #1; #1;
    #1; #1;
    #1; #1;
    #1; #1;
    #1; #1;
    #1; #1;
    #1; #1;
    #1; #1;
    #1; #1;
    #1; #1;
    #1; #1; //aqui ya muestra el llevo 

    $display("\nPrueba #3: Cuenta de tres en tres hacia abajo");
    $display("ENB   MODO   D        Q       RCO");

    ENB = 1'b1;
    MODO = 2'b01;
    D[3:0] = 4'b0000;

    #1;#1;
    MODO = 2'b10;

    #1; #1;
    #1; #1;
    #1; #1;
    #1; #1;
    #1; #1;
    #1; #1;
    #1; #1;
    #1; #1;
    #1; #1;
    #1; #1;
    #1; #1;

    $display("\nPrueba #5: Carga en paralelo");
    $display("ENB   MODO   D     Q       RCO");

    ENB = 1'b1;
    MODO = 2'b11;
    D[3:0] = 4'bxxxx;
    #1; #1;

    D[3:0] = 4'b0000; 
    #1; #1;

    D[3:0] += 1'b1; 
    #1; #1;

    D[3:0] += 1'b1; 
    #1; #1;
    D[3:0] += 1'b1; 
    #1; #1;
    D[3:0] += 1'b1; 
    #1; #1;
    D[3:0] += 1'b1; 
    #1; #1;
    D[3:0] += 1'b1; 
    #1; #1;
    D[3:0] += 1'b1; 
    #1; #1;
    D[3:0] += 1'b1;
    #1; #1;
    D[3:0] += 1'b1; 
    #1; #1;
    D[3:0] += 1'b1; 
    #1; #1;
    D[3:0] += 1'b1; 
    #1; #1;
    D[3:0] += 1'b1; 
    #1; #1;
    D[3:0] += 1'b1; 
    #1; #1;
    D[3:0] += 1'b1; 
    #1; #1;
    D[3:0] += 1'b1; 
    #1; #1;


    D[3:0] = 4'bxxxx;
    ENB = 1'b0;

    #1; #1;

    #5 $finish;


end */
endmodule 


////////////////////////////////////////////////////////
module tester16 (
    output reg CLK,
    output reg ENB, 
    output reg [1:0] MODO,
    output reg [15:0] entrada,
    input RCO,
    input RCO162,
    input RCO163, 
    input RCO164,
    input [15:0] salida
);

/*Creacion del reloj, en este apartado de codigo se inicializa el reloj
donde este cambia cada segundo de tiempo, siendo 0 en uno y 1 en otro
y asi hasta terminar de correr las pruebas*/

always begin
    CLK = 1'b0; #1;
    CLK = 1'b1; #1;
end

// Ejecucion de pruebas

  initial begin
    $display("Prueba #1: Cuenta ascendente");
    $display("ENB    MODO   D        Q       RCO");

    //primera instruccion 
    ENB = 1'b1; //activo el enable por que quiero que este empieza a cambiar
    entrada[15:0] = 16'h0000;
    MODO = 2'b11;
    entrada[15:0] = 16'h0000;

    //segunda y tercera instruccion
    //Con esta se pretende enviar el flanco activo en CLK y establecer el MODO igual a  2'b00
    #1; #1;
    MODO = 2'b00; // Esta en 0000 para iniciar

    // se envian 16 flancos de reloj
    /*Para este caso es muy importante que tomemos en cuenta que el RCO no sera igual a 1, hasta que a 1111 no se le sume 1, en este caso ya tomaria el llevo y RCO = 1 */
    #1; #1;
    #1; #1;
    #1; #1;
    #1; #1;
    #1; #1; 
    #1; #1;
    #1; #1;
    #1; #1;
    #1; #1;
    #1; #1;
    #1; #1;
    #1; #1;
    #1; #1;
    #1; #1;
    #1; #1;
    #1; #1; //
    #1; #1;
    #1; #1;
    #1; #1;
    #1; #1;
    #1; #1;
    #1; #1;
    #1; #1;
///////////////////////_ CUENTA DESCENDENTE 16BITS _///////////////////////////////////////
    $display("\nPrueba #2: Cuenta descendente");
    $display("ENB   MODO   D        Q       RCO");

    //primera instruccion 
    ENB = 1'b1; //activo el enable por que quiero que este empieza a cambiar
    MODO = 2'b11;
    entrada[15:0] = 16'hffff; 

    //segunda y tercera instruccion
    /*Con esta se pretende enviar el flanco activo en CLK
    y establecer el MODO igual a  2'b00*/
    #1; #1;

    MODO = 2'b01; // Esta en 0000 para iniciar

    // se envian 16 flancos de reloj
    #1; #1;
    #1; #1;
    #1; #1;
    #1; #1;
    #1; #1; 
    #1; #1;
    #1; #1;
    #1; #1;
    #1; #1;
    #1; #1;
    #1; #1;
    #1; #1;
    #1; #1;
    #1; #1;
    #1; #1;
    #1; #1;

///////////////////////_ CUENTA DE TRES EN TRES HACIA ABAJO 16BITS _///////////////////////////////////////
    $display("\nPrueba #3: Cuenta de tres en tres hacia abajo");
    $display("ENB   MODO   D        Q       RCO");

     #1; #1;
    ENB = 1'b1;
    MODO = 2'b11;
    entrada[15:0] = 16'hffff;


    #1;#1;
    MODO = 2'b10;

    #1; #1;
    #1; #1;
    #1; #1;
    #1; #1;
    #1; #1;
    #1; #1;
    #1; #1;
    #1; #1;
    #1; #1;
    #1; #1;
    #1; #1;
    #1; #1;
    #1; #1;
    #1; #1;
    #1; #1;
    #1; #1;
    #1; #1;
    #1; #1;
    #1; #1;
    #1; #1;




   $display("\nPrueba #5: Carga en paralelo");
    $display("ENB   MODO   D     Q       RCO");

    ENB = 1'b1;
    MODO = 2'b11;
    entrada[15:0] = 16'hxxxx;
    #1; #1;

    entrada[15:0] = 16'h0000; 
    #1; #1;

    entrada[15:0] += 1'b1; 
    #1; #1;

    entrada[15:0] += 1'b1;  
    #1; #1;
    entrada[15:0] += 1'b1; 
    #1; #1;
    entrada[15:0] += 1'b1;  
    #1; #1;
    entrada[15:0] += 1'b1; 
    #1; #1;
    entrada[15:0] += 1'b1;  
    #1; #1;
    entrada[15:0] += 1'b1;  
    #1; #1;
    entrada[15:0] += 1'b1; 
    #1; #1;
    entrada[15:0] += 1'b1;  
    #1; #1;
    entrada[15:0] += 1'b1; 
    #1; #1;
    entrada[15:0] += 1'b1;  
    #1; #1;
    entrada[15:0] += 1'b1;  
    #1; #1;
    entrada[15:0] += 1'b1;  
    #1; #1;
    entrada[15:0] += 1'b1; 
    #1; #1;
    entrada[15:0] += 1'b1;  
    #1; #1;
    entrada[15:0] += 1'b1;  
    #1; #1;
    entrada[15:0] += 1'b1;  
    #1; #1;
    entrada[15:0] += 1'b1;  


    //entrada[15:0] = 16'hxxxx;
    //ENB = 1'b0;

    //#1; #1; 

    #2 $finish;



end 
endmodule

ff.v

/* flip flop tipo D de n bits disparado por flanco
   creciente de clk con entrada de habilitacion enb.
   */
module FF #(parameter BITS = 1)
(
    input clk,
    input enb,
    input [BITS-1:0] d,
    output reg [BITS-1:0] q
);

/* en cada flanco creciente se actualiza la salida
   q con el valor en d si la enb esta habilitado.
   */
always @(posedge clk) begin
    if (enb == 1'b1)
        q <= d;
end

endmodule

contador.v
`include "ff.v" //archivo de flipflop

module contador (
    input CLK,
    input ENB,
    input [1:0] MODO,
    input [3:0] D,
    output [3:0] Q,
    output RCO 
);

reg [3:0] d_In;
reg d_Out;

/* Utilizando las senales MODO[1:0] como de seleccion,
se determina el valor de d_In y d_Out, cada uno de los
casos contiene al numero de modo, siendo por ejemplo:
3'b00, refiriendose al MODO=00 donde en este caso ocurre Q+1, y
asi sucesivamente. 
*/
initial begin 
    d_In = 4'b0000;
end

always @* begin
    case (MODO[1:0])
    //   caso         valor de RCO     valor de D[3:0]
        2'b00 : begin d_Out = 1'b0;  d_In = Q+1; 
            if (Q[3:0] == 4'b1111)
            begin 
                d_Out = 1'b1; 
            end else begin
                d_Out = 1'b0;
            end
        end // CUENTA ASCENDENTE
        2'b01 : begin d_Out = 1'b0;  d_In = Q-1; 
            if (Q[3:0] == 4'b0000)
            begin
                d_Out = 1'b1;
            end else begin
                d_Out = 1'b0;
            end
        end // CUENTA DESCENDENTE
        2'b10 : begin d_Out = 1'b0;  d_In = Q-3; end // CUENTA DE TRES EN TRES HACIA ABAJO
        2'b11 : begin d_Out = 1'b0;  d_In = D; 
            if (Q[3:0] == 4'b1111)
            begin 
                d_Out = 1; 
            end else begin
                d_Out = 1'b0;
            end end // CARGA EN PARALELO
        default: begin d_Out = d_Out; d_In = d_In; end // no cambiar los valores en otro caso.
    endcase
end

/*En esta seccion de codigo nombramos los ff hechos, donde se nombran luego de
incluirr el archivo principal en la primera linea de codigo. Es importante mencionar
que se hace uso de una etiqueta el cual clasificara el proceso que se ejecuta
por lo que se veria de la siguiente manera: NOMBRE_MODULO etiqueta*/

/*Nota importante: .BITS(4), hace referencia a algo mencionado en el archivo ff.v,
donde a lo que hace referencia es a 4 bits.*/


FF #(.BITS(4)) DFF_4bits(.clk(CLK), .enb(ENB), .d(d_In[3:0]), .q(Q[3:0])); // Registro de 4bits para Q[3:0]
FF DFF_1bit(.clk(CLK), .enb(ENB), .d(d_Out), .q(RCO)); // Registro de 1bit para RCO

endmodule

module contador16 (
    input CLK,
    input ENB,
    input [1:0] MODO,
    input [15:0] entrada,
    output [15:0] salida,
    output RCO, 
    output RCO162, 
    output RCO163, 
    output RCO164 

); 

reg d_Out1;
reg d_Out2;
reg d_Out3;
reg d_Out4;


FF DFF_1bit1(.clk(CLK), .enb(ENB), .d(d_Out1), .q(RCO)); // Registro de 1bit para RCO */
FF DFF_1bit2(.clk(CLK), .enb(ENB), .d(d_Out2), .q(RCO162)); // Registro de 1bit para RCO
FF DFF_1bit3(.clk(CLK), .enb(ENB), .d(d_Out3), .q(RCO163)); // Registro de 1bit para RCO
FF DFF_1bit4(.clk(CLK), .enb(ENB), .d(d_Out4), .q(RCO164)); // Registro de 1bit para RCO 

contador contador1(
    .CLK(CLK),
    .ENB(ENB), 
    .MODO(MODO[1:0]), 
    .D(entrada[3:0]), 
    .Q(salida[3:0]),
    .RCO(RCO)
);

wire clk2;
wire modo11;
assign modo11 = (MODO == 2'b11);
assign modo00 = (MODO == 2'b00);
assign clk2 = CLK && modo11 || RCO && !modo11;

always @* begin

    case(MODO[1:0]) 
        2'b00: begin 
            if (entrada[15:0] == 16'b1111_1111_1111_1111)
                begin 
                    d_Out1 = 1'b1;
                end else begin
                    d_Out1 = 1'b0; 
                end
            end
     
        2'b01: begin 
            if (entrada[15:0] == 16'b0000_0000_0000_0000)
                begin 
                    d_Out1 = 1'b1;
                end else begin
                    d_Out1 = 1'b0; 
                end
            end

        2'b10: begin 
            if (entrada[15:0] == 16'b0000_0000_0000_0000 || entrada[15:0] == 16'b0000_0000_0000_0001 || entrada[15:0] == 16'b0000_0000_0000_0010 )
                begin 
                    d_Out1 = 1'b1;
                end else begin
                    d_Out1 = 1'b0; 
                end
            end
    endcase
    end

contador contador2(
    .CLK(clk2),
    .ENB(ENB), 
    .MODO(MODO[1:0]), 
    .D(entrada[7:4]), 
    .Q(salida[7:4]),
    .RCO(RCO162)
);

wire clk3;
wire modo113;
assign modo113 = (MODO == 2'b11);
assign clk3 = clk2 && modo113 || RCO162 && !modo113;

always @* begin
    case(MODO[1:0]) 
        2'b00: begin 
                if (entrada[15:0] == 16'b1111_1111_1111_1111)
                    begin 
                        d_Out2 = 1'b1;
                    end else begin
                        d_Out2 = 1'b0; 
                    end

            end
    2'b01: begin 
            if (entrada[15:0] == 16'b0000_0000_0000_0000)
                begin 
                    d_Out2 = 1'b1;
                end else begin
                    d_Out2 = 1'b0; 
                end

            end
    2'b10: begin 
            if (entrada[15:0] == 16'b0000_0000_0000_0000 || entrada[15:0] == 16'b0000_0000_0000_0001 || entrada[15:0] == 16'b0000_0000_0000_0010 )
                begin 
                    d_Out2 = 1'b1;
                end else begin
                    d_Out2 = 1'b0; 
                end
            end
    endcase
    end


contador contador3(
    .CLK(clk3),
    .ENB(ENB), 
    .MODO(MODO[1:0]), 
    .D(entrada[11:8]), 
    .Q(salida[11:8]),
    .RCO(RCO163)
);

wire clk4;
wire modo114;
assign modo114 = (MODO == 2'b11);
assign clk4 = clk3 && modo114 || RCO163 && !modo114;

    always @* begin
    case(MODO[1:0]) 
        2'b00: begin 
    
            if (entrada[15:0] == 16'b1111_1111_1111_1111)
                begin 
                    d_Out3 = 1'b1;
                end else begin
                    d_Out3 = 1'b0; 
                end

                end
     
        2'b01: begin 

            if (entrada[15:0] == 16'b0000_0000_0000_0000)
                begin 
                    d_Out3 = 1'b1;
                end else begin
                    d_Out3 = 1'b0; 
                end

                end

        2'b10: begin 

            if (entrada[15:0] == 16'b0000_0000_0000_0000 || entrada[15:0] == 16'b0000_0000_0000_0001 || entrada[15:0] == 16'b0000_0000_0000_0010 )
                begin 
                    d_Out3 = 1'b1;
                end else begin
                   d_Out3 = 1'b0; 
                end

                end

    endcase

    end

contador contador4(
    .CLK   (clk4),
    .ENB   (ENB), 
    .MODO  (MODO[1:0]), 
    .D     (entrada[15:12]), 
    .Q     (salida[15:12]),
    .RCO   (RCO164)
);

/*always @* begin
        case(MODO[1:0]) 
        2'b00: begin 
        
            if (entrada[15:0] == 16'b1111_1111_1111_1111)
                begin 
                    d_Out4 = 1'b1;
                end else begin
                    d_Out4 = 1'b0; 
                end
    
                end
         
        2'b01: begin 
            if (entrada[15:0] == 16'b0000_0000_0000_0000)
                begin 
                    d_Out4 = 1'b1;
                end else begin
                    d_Out4 = 1'b0; 
                end
    
        end
    
        2'b10: begin 
            if (entrada[15:0] == 16'h0000 || entrada[15:0] == 16'b0000_0000_0000_0001 || entrada[15:0] == 16'b0000_0000_0000_0010 )
                begin 
                    d_Out4 = 1'b1;
                end else begin
                    d_Out4 = 1'b0; 
                end
            end
    
        endcase

        end*/
endmodule

testbench.v
`include "contador.v"
`include "probador.v"


// Banco de pruebas para el registro de cuatro bits y el probador
module tb;
    wire clk, enb, RCO;
    wire [1:0] modo;
    wire [3:0] D; 
    wire [3:0] Q;


    contador DUT(
        .CLK(clk), 
        .ENB(enb),              
        .MODO(modo[1:0]), 
        .D(D[3:0]), 
        .Q(Q[3:0]),
        .RCO(RCO)
    );

    /* se instancia un probador
       */
    tester test(
        .CLK(clk), 
        .ENB(enb),
        .MODO(modo[1:0]), 
        .D(D[3:0]), 
        .Q(Q[3:0]), 
        .RCO(RCO)
);

/* para generar las ondas y
    y visualizar en gtkwave
    */
    initial begin
        $dumpfile("testbench.vcd");
        $dumpvars;
    end

    /* para mostrar (vvp) los valores
    de las entradas y salidas
    del registro en cada flanco
    activo de reloj
    */
    /*always @(posedge clk) begin
        $display(" %b     %b     %b      %b   %b", enb, modo, D, Q, RCO);
    end*/

endmodule


module tb16;
    wire clk, enb, RCO, RCO162, RCO163, RCO164;
    wire [1:0] modo;
    wire [15:0] D; 
    wire [15:0] Q;


    contador16 DUT16 (
        .CLK(clk), 
        .ENB(enb),
        .MODO(modo[1:0]), 
        .entrada(D[15:0]), 
        .salida(Q[15:0]),
        .RCO(RCO), 
        .RCO162(RCO162), 
        .RCO163(RCO163),
        .RCO164(RCO164)
    );

    /* se instancia un probador
       */
    tester16 test16(
        .CLK(clk), .ENB(enb),
        .MODO(modo[1:0]),
        .entrada(D[15:0]), 
        .salida(Q[15:0]), 
        .RCO(RCO), 
        .RCO162(RCO162), 
        .RCO163(RCO163), 
        .RCO164(RCO164)
    );

/* para generar las ondas y visualizar en gtkwave*/
    /*initial begin
        $dumpfile("testbench.vcd");
        $dumpvars;
    end*/

    always @(posedge clk) begin
        $display("enb=%b     modo=%b     D16=%b      Q16=%b   RCO=%b", enb, modo, D, Q, RCO);
    end


endmodule

testbench.vcd
$date
	Fri Sep  9 08:51:02 2022
$end
$version
	Icarus Verilog
$end
$timescale
	1ns
$end
$scope module tb $end
$var wire 2 ! modo [1:0] $end
$var wire 1 " enb $end
$var wire 1 # clk $end
$var wire 1 $ RCO $end
$var wire 4 % Q [3:0] $end
$var wire 4 & D [3:0] $end
$scope module DUT $end
$var wire 1 $ RCO $end
$var wire 4 ' Q [3:0] $end
$var wire 2 ( MODO [1:0] $end
$var wire 1 " ENB $end
$var wire 4 ) D [3:0] $end
$var wire 1 # CLK $end
$var reg 4 * d_In [3:0] $end
$var reg 1 + d_Out $end
$scope module DFF_1bit $end
$var wire 1 + d $end
$var wire 1 " enb $end
$var wire 1 # clk $end
$var reg 1 $ q $end
$upscope $end
$scope module DFF_4bits $end
$var wire 4 , d [3:0] $end
$var wire 1 " enb $end
$var wire 1 # clk $end
$var reg 4 - q [3:0] $end
$upscope $end
$upscope $end
$scope module test $end
$var wire 4 . Q [3:0] $end
$var wire 1 $ RCO $end
$var reg 1 # CLK $end
$var reg 4 / D [3:0] $end
$var reg 1 " ENB $end
$var reg 2 0 MODO [1:0] $end
$upscope $end
$upscope $end
$scope module tb16 $end
$var wire 1 1 RCO $end
$var wire 1 2 RCO162 $end
$var wire 1 3 RCO163 $end
$var wire 1 4 RCO164 $end
$var wire 2 5 modo [1:0] $end
$var wire 1 6 enb $end
$var wire 1 7 clk $end
$var wire 16 8 Q [15:0] $end
$var wire 16 9 D [15:0] $end
$scope module DUT16 $end
$var wire 1 1 RCO $end
$var wire 1 2 RCO162 $end
$var wire 1 3 RCO163 $end
$var wire 1 4 RCO164 $end
$var wire 1 : clk2 $end
$var wire 1 ; clk3 $end
$var wire 1 < clk4 $end
$var wire 16 = salida [15:0] $end
$var wire 1 > modo114 $end
$var wire 1 ? modo113 $end
$var wire 1 @ modo11 $end
$var wire 1 A modo00 $end
$var wire 16 B entrada [15:0] $end
$var wire 2 C MODO [1:0] $end
$var wire 1 6 ENB $end
$var wire 1 7 CLK $end
$var reg 1 D d_Out1 $end
$var reg 1 E d_Out2 $end
$var reg 1 F d_Out3 $end
$var reg 1 G d_Out4 $end
$scope module DFF_1bit1 $end
$var wire 1 D d $end
$var wire 1 6 enb $end
$var wire 1 7 clk $end
$var reg 1 H q $end
$upscope $end
$scope module DFF_1bit2 $end
$var wire 1 E d $end
$var wire 1 6 enb $end
$var wire 1 7 clk $end
$var reg 1 I q $end
$upscope $end
$scope module DFF_1bit3 $end
$var wire 1 F d $end
$var wire 1 6 enb $end
$var wire 1 7 clk $end
$var reg 1 J q $end
$upscope $end
$scope module DFF_1bit4 $end
$var wire 1 G d $end
$var wire 1 6 enb $end
$var wire 1 7 clk $end
$var reg 1 K q $end
$upscope $end
$scope module contador1 $end
$var wire 4 L D [3:0] $end
$var wire 1 1 RCO $end
$var wire 4 M Q [3:0] $end
$var wire 2 N MODO [1:0] $end
$var wire 1 6 ENB $end
$var wire 1 7 CLK $end
$var reg 4 O d_In [3:0] $end
$var reg 1 P d_Out $end
$scope module DFF_1bit $end
$var wire 1 P d $end
$var wire 1 6 enb $end
$var wire 1 7 clk $end
$var reg 1 Q q $end
$upscope $end
$scope module DFF_4bits $end
$var wire 4 R d [3:0] $end
$var wire 1 6 enb $end
$var wire 1 7 clk $end
$var reg 4 S q [3:0] $end
$upscope $end
$upscope $end
$scope module contador2 $end
$var wire 1 : CLK $end
$var wire 4 T D [3:0] $end
$var wire 1 2 RCO $end
$var wire 4 U Q [3:0] $end
$var wire 2 V MODO [1:0] $end
$var wire 1 6 ENB $end
$var reg 4 W d_In [3:0] $end
$var reg 1 X d_Out $end
$scope module DFF_1bit $end
$var wire 1 : clk $end
$var wire 1 X d $end
$var wire 1 6 enb $end
$var reg 1 Y q $end
$upscope $end
$scope module DFF_4bits $end
$var wire 1 : clk $end
$var wire 4 Z d [3:0] $end
$var wire 1 6 enb $end
$var reg 4 [ q [3:0] $end
$upscope $end
$upscope $end
$scope module contador3 $end
$var wire 1 ; CLK $end
$var wire 4 \ D [3:0] $end
$var wire 1 3 RCO $end
$var wire 4 ] Q [3:0] $end
$var wire 2 ^ MODO [1:0] $end
$var wire 1 6 ENB $end
$var reg 4 _ d_In [3:0] $end
$var reg 1 ` d_Out $end
$scope module DFF_1bit $end
$var wire 1 ; clk $end
$var wire 1 ` d $end
$var wire 1 6 enb $end
$var reg 1 a q $end
$upscope $end
$scope module DFF_4bits $end
$var wire 1 ; clk $end
$var wire 4 b d [3:0] $end
$var wire 1 6 enb $end
$var reg 4 c q [3:0] $end
$upscope $end
$upscope $end
$scope module contador4 $end
$var wire 1 < CLK $end
$var wire 4 d D [3:0] $end
$var wire 1 4 RCO $end
$var wire 4 e Q [3:0] $end
$var wire 2 f MODO [1:0] $end
$var wire 1 6 ENB $end
$var reg 4 g d_In [3:0] $end
$var reg 1 h d_Out $end
$scope module DFF_1bit $end
$var wire 1 < clk $end
$var wire 1 h d $end
$var wire 1 6 enb $end
$var reg 1 i q $end
$upscope $end
$scope module DFF_4bits $end
$var wire 1 < clk $end
$var wire 4 j d [3:0] $end
$var wire 1 6 enb $end
$var reg 4 k q [3:0] $end
$upscope $end
$upscope $end
$upscope $end
$scope module test16 $end
$var wire 1 1 RCO $end
$var wire 1 2 RCO162 $end
$var wire 1 3 RCO163 $end
$var wire 1 4 RCO164 $end
$var wire 16 l salida [15:0] $end
$var reg 1 7 CLK $end
$var reg 1 6 ENB $end
$var reg 2 m MODO [1:0] $end
$var reg 16 n entrada [15:0] $end
$upscope $end
$upscope $end
$enddefinitions $end
#0
$dumpvars
b0 n
b11 m
bx l
bx k
b0 j
xi
0h
b0 g
b11 f
bx e
b0 d
bx c
b0 b
xa
0`
b0 _
b11 ^
bx ]
b0 \
bx [
b0 Z
xY
0X
b0 W
b11 V
bx U
b0 T
bx S
b0 R
xQ
0P
b0 O
b11 N
bx M
b0 L
xK
xJ
xI
xH
xG
xF
xE
xD
b11 C
b0 B
0A
1@
1?
1>
bx =
0<
0;
0:
b0 9
bx 8
07
16
b11 5
x4
x3
x2
x1
bx 0
bx /
bx .
bx -
b0 ,
x+
b0 *
bx )
bx (
bx '
bx &
bx %
x$
0#
x"
bx !
$end
#1
b0 e
b0 k
0i
b0 ]
b0 c
0a
b0 U
b0 [
0Y
b0 8
b0 =
b0 l
b0 M
b0 S
0Q
1<
1;
1:
17
1#
#2
x<
x;
x:
0D
0E
0F
b1 O
b1 R
b1 W
b1 Z
b1 _
b1 b
b1 g
b1 j
0>
0?
1A
0@
b0 5
b0 C
b0 N
b0 V
b0 ^
b0 f
b0 m
07
0#
#3
0<
0;
0:
b10 O
b10 R
b1 8
b1 =
b1 l
b1 M
b1 S
03
0J
02
0I
01
0H
17
1#
#4
07
0#
#5
b11 O
b11 R
b10 8
b10 =
b10 l
b10 M
b10 S
17
1#
#6
07
0#
#7
b100 O
b100 R
b11 8
b11 =
b11 l
b11 M
b11 S
17
1#
#8
07
0#
#9
b101 O
b101 R
b100 8
b100 =
b100 l
b100 M
b100 S
17
1#
#10
07
0#
#11
b110 O
b110 R
b101 8
b101 =
b101 l
b101 M
b101 S
17
1#
#12
07
0#
#13
b111 O
b111 R
b110 8
b110 =
b110 l
b110 M
b110 S
17
1#
#14
07
0#
#15
b1000 O
b1000 R
b111 8
b111 =
b111 l
b111 M
b111 S
17
1#
#16
07
0#
#17
b1001 O
b1001 R
b1000 8
b1000 =
b1000 l
b1000 M
b1000 S
17
1#
#18
07
0#
#19
b1010 O
b1010 R
b1001 8
b1001 =
b1001 l
b1001 M
b1001 S
17
1#
#20
07
0#
#21
b1011 O
b1011 R
b1010 8
b1010 =
b1010 l
b1010 M
b1010 S
17
1#
#22
07
0#
#23
b1100 O
b1100 R
b1011 8
b1011 =
b1011 l
b1011 M
b1011 S
17
1#
#24
07
0#
#25
b1101 O
b1101 R
b1100 8
b1100 =
b1100 l
b1100 M
b1100 S
17
1#
#26
07
0#
#27
b1110 O
b1110 R
b1101 8
b1101 =
b1101 l
b1101 M
b1101 S
17
1#
#28
07
0#
#29
b1111 O
b1111 R
b1110 8
b1110 =
b1110 l
b1110 M
b1110 S
17
1#
#30
07
0#
#31
1P
b0 O
b0 R
b1111 8
b1111 =
b1111 l
b1111 M
b1111 S
17
1#
#32
07
0#
#33
b10 W
b10 Z
b1 U
b1 [
x:
b1 O
b1 R
0P
b10000 8
b10000 =
b10000 l
b0 M
b0 S
x1
1Q
17
1#
#34
07
0#
#35
0:
b10 O
b10 R
01
0Q
b10001 8
b10001 =
b10001 l
b1 M
b1 S
17
1#
#36
07
0#
#37
b11 O
b11 R
b10010 8
b10010 =
b10010 l
b10 M
b10 S
17
1#
#38
07
0#
#39
b100 O
b100 R
b10011 8
b10011 =
b10011 l
b11 M
b11 S
17
1#
#40
07
0#
#41
b101 O
b101 R
b10100 8
b10100 =
b10100 l
b100 M
b100 S
17
1#
#42
07
0#
#43
b110 O
b110 R
b10101 8
b10101 =
b10101 l
b101 M
b101 S
17
1#
#44
07
0#
#45
b111 O
b111 R
b10110 8
b10110 =
b10110 l
b110 M
b110 S
17
1#
#46
07
0#
#47
b1000 O
b1000 R
b10111 8
b10111 =
b10111 l
b111 M
b111 S
17
1#
#48
b1111 d
b1111 \
b1111 T
b1111 L
b1111 O
b1111 R
b1111 W
b1111 Z
b1111 _
b1111 b
b1111 g
b1111 j
b1111111111111111 9
b1111111111111111 B
b1111111111111111 n
1>
1?
0A
1@
b11 5
b11 C
b11 N
b11 V
b11 ^
b11 f
b11 m
07
0#
#49
1h
1`
1X
1P
b1111 e
b1111 k
b1111 ]
b1111 c
b1111 U
b1111 [
b1111111111111111 8
b1111111111111111 =
b1111111111111111 l
b1111 M
b1111 S
1<
1;
1:
17
1#
#50
0<
0;
0:
b1110 O
b1110 R
0P
b1110 W
b1110 Z
0X
b1110 _
b1110 b
0`
b1110 g
b1110 j
0h
0>
0?
0@
b1 5
b1 C
b1 N
b1 V
b1 ^
b1 f
b1 m
07
0#
#51
b1101 O
b1101 R
b1111111111111110 8
b1111111111111110 =
b1111111111111110 l
b1110 M
b1110 S
17
1#
#52
07
0#
#53
b1100 O
b1100 R
b1111111111111101 8
b1111111111111101 =
b1111111111111101 l
b1101 M
b1101 S
17
1#
#54
07
0#
#55
b1011 O
b1011 R
b1111111111111100 8
b1111111111111100 =
b1111111111111100 l
b1100 M
b1100 S
17
1#
#56
07
0#
#57
b1010 O
b1010 R
b1111111111111011 8
b1111111111111011 =
b1111111111111011 l
b1011 M
b1011 S
17
1#
#58
07
0#
#59
b1001 O
b1001 R
b1111111111111010 8
b1111111111111010 =
b1111111111111010 l
b1010 M
b1010 S
17
1#
#60
07
0#
#61
b1000 O
b1000 R
b1111111111111001 8
b1111111111111001 =
b1111111111111001 l
b1001 M
b1001 S
17
1#
#62
07
0#
#63
b111 O
b111 R
b1111111111111000 8
b1111111111111000 =
b1111111111111000 l
b1000 M
b1000 S
17
1#
#64
07
0#
#65
b110 O
b110 R
b1111111111110111 8
b1111111111110111 =
b1111111111110111 l
b111 M
b111 S
17
1#
#66
07
0#
#67
b101 O
b101 R
b1111111111110110 8
b1111111111110110 =
b1111111111110110 l
b110 M
b110 S
17
1#
#68
07
0#
#69
b100 O
b100 R
b1111111111110101 8
b1111111111110101 =
b1111111111110101 l
b101 M
b101 S
17
1#
#70
07
0#
#71
b11 O
b11 R
b1111111111110100 8
b1111111111110100 =
b1111111111110100 l
b100 M
b100 S
17
1#
#72
07
0#
#73
b10 O
b10 R
b1111111111110011 8
b1111111111110011 =
b1111111111110011 l
b11 M
b11 S
17
1#
#74
07
0#
#75
b1 O
b1 R
b1111111111110010 8
b1111111111110010 =
b1111111111110010 l
b10 M
b10 S
17
1#
#76
07
0#
#77
b0 O
b0 R
b1111111111110001 8
b1111111111110001 =
b1111111111110001 l
b1 M
b1 S
17
1#
#78
07
0#
#79
1P
b1111 O
b1111 R
b1111111111110000 8
b1111111111110000 =
b1111111111110000 l
b0 M
b0 S
17
1#
#80
07
0#
#81
b1101 W
b1101 Z
b1110 U
b1110 [
x:
b1110 O
b1110 R
0P
b1111111111101111 8
b1111111111101111 =
b1111111111101111 l
b1111 M
b1111 S
x1
1Q
17
1#
#82
07
0#
#83
0:
b1101 O
b1101 R
01
0Q
b1111111111101110 8
b1111111111101110 =
b1111111111101110 l
b1110 M
b1110 S
17
1#
#84
b1111 O
b1111 R
b1111 W
b1111 Z
1`
b1111 _
b1111 b
1h
b1111 g
b1111 j
1>
1?
1@
b11 5
b11 C
b11 N
b11 V
b11 ^
b11 f
b11 m
07
0#
#85
1X
1P
1i
x3
1a
b1111 U
b1111 [
b1111111111111111 8
b1111111111111111 =
b1111111111111111 l
b1111 M
b1111 S
1<
1;
1:
17
1#
