contador16.v
`include "contador.v"

module contador16 (
    input CLK,
    input ENB,
    input [1:0] MODO,
    input [15:0] entrada,
    output [15:0] salida,
    output RCO);

wire RCO0, RCO1, RCO2;

contador contador1(
    .CLK    (CLK),
    .ENB    (ENB), 
    .MODO   (MODO[1:0]), 
    .D      (entrada[3:0]), 
    .Q      (salida[3:0]),
    .RCO    (RCO0));

contador contador2(
    .CLK    (RCO0),
    .ENB    (ENB), 
    .MODO   (MODO[1:0]), 
    .D      (entrada[7:4]), 
    .Q      (salida[7:4]),
    .RCO    (RCO1));

contador contador3(
    .CLK    (RCO1),
    .ENB    (ENB), 
    .MODO   (MODO[1:0]), 
    .D      (entrada[11:8]), 
    .Q      (salida[11:8]),
    .RCO    (RCO2));

contador contador4(
    .CLK    (RCO3),
    .ENB    (ENB), 
    .MODO   (MODO[1:0]), 
    .D      (entrada[15:12]), 
    .Q      (salida[15:12]),
    .RCO    (RCO));

endmodule

probador.v
`timescale 1ns/1ns // escala de tiempo

/*Probador del registro de cuatro
   bits*/
module tester (
    output reg CLK,
    output reg ENB,
    output reg [1:0] MODO,
    output reg [3:0] D,
    input [3:0] Q,
    input RCO
);

/*Creacion del reloj, en este apartado de codigo se inicializa el reloj
donde este cambia cada segundo de tiempo, siendo 0 en uno y 1 en otro
y asi hasta terminar de correr las pruebas*/

always begin
    CLK = 1'b0; #1;
    CLK = 1'b1; #1;
end

// Ejecucion de pruebas

initial begin
    $display("Prueba #1: Cuenta ascendente");
    $display("ENB    MODO   D        Q       RCO");

    //primera instruccion 
    ENB = 1'b1; //activo el enable por que quiero que este empieza a cambiar
    MODO = 2'b11;
    D[3:0] = 4'b0000;

    //segunda y tercera instruccion
    /*Con esta se pretende enviar el flanco activo en CLK
    y establecer el MODO igual a  2'b00*/
    #1; #1;
    MODO = 2'b00; // Esta en 0000 para iniciar

    // se envian 16 flancos de reloj
    /*Para este caso es muy importante que tomemos en cuenta que el RCO no sera
    igual a 1, hasta que a 1111 no se le sume 1, en este caso ya tomaria el llevo
    y RCO = 1 */
    #1; #1;
    #1; #1;
    #1; #1;
    #1; #1;
    #1; #1;
    #1; #1;
    #1; #1;
    #1; #1;
    #1; #1;
    #1; #1;
    #1; #1;
    #1; #1;
    #1; #1;
    #1; #1;
    #1; #1;
    #1; #1; 
    #1; #1; //aqui ya muestra el llevo 

    $display("\nPrueba #2: Cuenta descendente");
    $display("ENB   MODO   D        Q       RCO");

    //primera instruccion 
    ENB = 1'b1; //activo el enable por que quiero que este empieza a cambiar
    //D[3:0] = 4'b0000;
    MODO = 2'b11;
    D[3:0] = 4'b0000;

    //segunda y tercera instruccion
    /*Con esta se pretende enviar el flanco activo en CLK
    y establecer el MODO igual a  2'b00*/
    #1; #1;
    MODO = 2'b01; // Esta en 0000 para iniciar

    // se envian 16 flancos de reloj
    #1; #1;
    #1; #1;
    #1; #1;
    #1; #1;
    #1; #1;
    #1; #1;
    #1; #1;
    #1; #1;
    #1; #1;
    #1; #1;
    #1; #1;
    #1; #1;
    #1; #1;
    #1; #1;
    #1; #1;
    #1; #1; 
    #1; #1; //aqui ya muestra el llevo 

    $finish;

end
endmodule

ff.v
/* flip flop tipo D de n bits disparado por flanco
   creciente de clk con entrada de habilitacion enb.
   */
module DFF_nbits_enb #(parameter BITS = 1)
(
    input clk,
    input enb,
    input [BITS-1:0] d,
    output reg [BITS-1:0] q
);

/* en cada flanco creciente se actualiza la salida
   q con el valor en d si la enb esta habilitado.
   */
always @(posedge clk) begin
    if (enb == 1'b1)
        q <= d;
end

endmodule

contador.v
`include "ff.v" //archivo de flipflop

module contador (
    input CLK,
    input ENB,
    input [1:0] MODO,
    input [3:0] D,
    output [3:0] Q,
    output RCO 
);

reg [3:0] d_In;
reg d_Out;




/* Utilizando las senales MODO[1:0] como de seleccion,
se determina el valor de d_In y d_Out, cada uno de los
casos contiene al numero de modo, siendo por ejemplo:
3'b00, refiriendose al MODO=00 donde en este caso ocurre Q+1, y
asi sucesivamente. 
*/
always @* begin
    case (MODO[1:0])
    //   caso         valor de RCO     valor de D[3:0]
        3'b00 : begin d_Out = 1'b0;  d_In = Q+1; /*aqui se puede meter lo del case*/end // CUENTA ASCENDENTE
        3'b01 : begin d_Out = 1'b0;  d_In = Q-1; end // CUENTA DESCENDENTE
        3'b10 : begin d_Out = 1'b0;  d_In = Q-3; end // CUENTA DE TRES EN TRES HACIA ABAJO
        3'b11 : begin d_Out = 1'b1;  d_In = D; end // CARGA EN PARALELO
        default: begin d_Out = d_Out; d_In = d_In; end // no cambiar los valores en otro caso.
    endcase
    /*case (Q[3:0])
    //   caso 
        4'b1111: begin d_Out = 1'b1; end
    endcase 
end

/*En esta seccion de codigo nombramos los ff hechos, donde se nombran luego de
incluirr el archivo principal en la primera linea de codigo. Es importante mencionar
que se hace uso de una etiqueta el cual clasificara el proceso que se ejecuta
por lo que se veria de la siguiente manera: NOMBRE_MODULO etiqueta*/

/*Nota importante: .BITS(4), hace referencia a algo mencionado en el archivo ff.v,
donde a lo que hace referencia es a 4 bits.*/

DFF_nbits_enb #(.BITS(4)) DFF_4bits(.clk(CLK), .enb(ENB), .d(d_In[3:0]), .q(Q[3:0])); // Registro de 4bits para Q[3:0]
DFF_nbits_enb DFF_1bit(.clk(CLK), .enb(ENB), .d(d_Out), .q(RCO)); // Registro de 1bit para RCO

endmodule

testbench.v
`include "contador.v"
`include "probador.v"
//`include "contador16.v"

/* banco de pruebas para el
   registro de cuatro bits
   y el probador
   */
module tb;
    wire clk, enb, RCO;
    wire [1:0] modo;
    wire [3:0] D; 
    wire [3:0] Q;


    contador DUT(.CLK(clk), .ENB(enb),
                      .MODO(modo[1:0]), .D(D[3:0]), .Q(Q[3:0]),
                      .RCO(RCO));

    /* se instancia un probador
       */
    tester test(.CLK(clk), .ENB(enb),
                .MODO(modo[1:0]), .D(D[3:0]), .Q(Q[3:0]), .RCO(RCO));

/* para generar las ondas y
    y visualizar en gtkwave
    */
    initial begin
        $dumpfile("testbench.vcd");
        $dumpvars;
    end

    /* para mostrar (vvp) los valores
    de las entradas y salidas
    del registro en cada flanco
    activo de reloj
    */
    always @(posedge clk) begin
        $display(" %b     %b     %b      %b   %b", enb, modo, D, Q, RCO);
    end

endmodule


module tb16;
    wire clk, enb, RCO, RCO162, RCO163, RCO164;
    wire [1:0] modo;
    wire [15:0] D; 
    wire [15:0] Q;


    contador16 DUT16 (.CLK(clk), .ENB(enb),
                      .MODO(modo[1:0]), .entrada(D[15:0]), .salida(Q[15:0]),
                      .RCO(RCO), .RCO162(RCO161), .RCO163(RCO163), .RCO164(RCO164));

    /* se instancia un probador
       */
    tester16 test16(.CLK(clk), .ENB(enb),
                .MODO(modo[1:0]),.entrada(D[15:0]), .salida(Q[15:0]), 
                .RCO(RCO), .RCO162(RCO161), .RCO163(RCO163), .RCO164(RCO164));

/* para generar las ondas y
    y visualizar en gtkwave
    */
    initial begin
        $dumpfile("testbench.vcd");
        $dumpvars;
    end

    /* para mostrar (vvp) los valores
    de las entradas y salidas
    del registro en cada flanco
    activo de reloj
    */
    always @(posedge clk) begin
        $display("enb=%b     modo=%b     D16=%b      Q16=%b   RCO=%b", enb, modo, D, Q, RCO162);
    end

endmodule

testbench.vcd
$date
	Thu Sep  1 15:21:34 2022
$end
$version
	Icarus Verilog
$end
$timescale
	1ns
$end
$scope module tb $end
$var wire 2 ! modo [1:0] $end
$var wire 1 " enb $end
$var wire 1 # clk $end
$var wire 1 $ RCO $end
$var wire 4 % Q [3:0] $end
$var wire 4 & D [3:0] $end
$scope module DUT $end
$var wire 1 $ RCO $end
$var wire 4 ' Q [3:0] $end
$var wire 2 ( MODO [1:0] $end
$var wire 1 " ENB $end
$var wire 4 ) D [3:0] $end
$var wire 1 # CLK $end
$var reg 4 * d_In [3:0] $end
$var reg 1 + d_Out $end
$scope module DFF_1bit $end
$var wire 1 + d $end
$var wire 1 " enb $end
$var wire 1 # clk $end
$var reg 1 $ q $end
$upscope $end
$scope module DFF_4bits $end
$var wire 4 , d [3:0] $end
$var wire 1 " enb $end
$var wire 1 # clk $end
$var reg 4 - q [3:0] $end
$upscope $end
$upscope $end
$scope module test $end
$var wire 4 . Q [3:0] $end
$var wire 1 $ RCO $end
$var reg 1 # CLK $end
$var reg 4 / D [3:0] $end
$var reg 1 " ENB $end
$var reg 2 0 MODO [1:0] $end
$upscope $end
$upscope $end
$enddefinitions $end
#0
$dumpvars
b11 0
b0 /
bx .
bx -
b0 ,
1+
b0 *
b0 )
b11 (
bx '
b0 &
bx %
x$
0#
1"
b11 !
$end
#1
b0 %
b0 '
b0 -
b0 .
1$
1#
#2
b1 *
b1 ,
0+
b0 !
b0 (
b0 0
0#
#3
b10 *
b10 ,
0$
b1 %
b1 '
b1 -
b1 .
1#
#4
0#
#5
b11 *
b11 ,
b10 %
b10 '
b10 -
b10 .
1#
#6
0#
#7
b100 *
b100 ,
b11 %
b11 '
b11 -
b11 .
1#
#8
0#
#9
b101 *
b101 ,
b100 %
b100 '
b100 -
b100 .
1#
#10
0#
#11
b110 *
b110 ,
b101 %
b101 '
b101 -
b101 .
1#
#12
0#
#13
b111 *
b111 ,
b110 %
b110 '
b110 -
b110 .
1#
#14
0#
#15
b1000 *
b1000 ,
b111 %
b111 '
b111 -
b111 .
1#
#16
0#
#17
b1001 *
b1001 ,
b1000 %
b1000 '
b1000 -
b1000 .
1#
#18
0#
#19
b1010 *
b1010 ,
b1001 %
b1001 '
b1001 -
b1001 .
1#
#20
0#
#21
b1011 *
b1011 ,
b1010 %
b1010 '
b1010 -
b1010 .
1#
#22
0#
#23
b1100 *
b1100 ,
b1011 %
b1011 '
b1011 -
b1011 .
1#
#24
0#
#25
b1101 *
b1101 ,
b1100 %
b1100 '
b1100 -
b1100 .
1#
#26
0#
#27
b1110 *
b1110 ,
b1101 %
b1101 '
b1101 -
b1101 .
1#
#28
0#
#29
b1111 *
b1111 ,
b1110 %
b1110 '
b1110 -
b1110 .
1#
#30
0#
#31
1+
b0 *
b0 ,
b1111 %
b1111 '
b1111 -
b1111 .
1#
#32
0#
#33
b1 *
b1 ,
0+
b0 %
b0 '
b0 -
b0 .
1$
1#
#34
0#
#35
b10 *
b10 ,
0$
b1 %
b1 '
b1 -
b1 .
1#
#36
b0 *
b0 ,
1+
b11 !
b11 (
b11 0
0#
#37
b0 %
b0 '
b0 -
b0 .
1$
1#
#38
b1111 *
b1111 ,
0+
b1 !
b1 (
b1 0
0#
#39
b1110 *
b1110 ,
0$
b1111 %
b1111 '
b1111 -
b1111 .
1#
#40
0#
#41
b1101 *
b1101 ,
b1110 %
b1110 '
b1110 -
b1110 .
1#
#42
0#
#43
b1100 *
b1100 ,
b1101 %
b1101 '
b1101 -
b1101 .
1#
#44
0#
#45
b1011 *
b1011 ,
b1100 %
b1100 '
b1100 -
b1100 .
1#
#46
0#
#47
b1010 *
b1010 ,
b1011 %
b1011 '
b1011 -
b1011 .
1#
#48
0#
#49
b1001 *
b1001 ,
b1010 %
b1010 '
b1010 -
b1010 .
1#
#50
0#
#51
b1000 *
b1000 ,
b1001 %
b1001 '
b1001 -
b1001 .
1#
#52
0#
#53
b111 *
b111 ,
b1000 %
b1000 '
b1000 -
b1000 .
1#
#54
0#
#55
b110 *
b110 ,
b111 %
b111 '
b111 -
b111 .
1#
#56
0#
#57
b101 *
b101 ,
b110 %
b110 '
b110 -
b110 .
1#
#58
0#
#59
b100 *
b100 ,
b101 %
b101 '
b101 -
b101 .
1#
#60
0#
#61
b11 *
b11 ,
b100 %
b100 '
b100 -
b100 .
1#
#62
0#
#63
b10 *
b10 ,
b11 %
b11 '
b11 -
b11 .
1#
#64
0#
#65
b1 *
b1 ,
b10 %
b10 '
b10 -
b10 .
1#
#66
0#
#67
b0 *
b0 ,
b1 %
b1 '
b1 -
b1 .
1#
#68
0#
#69
b1111 *
b1111 ,
b0 %
b0 '
b0 -
b0 .
1#
#70
0#
#71
b1110 *
b1110 ,
b1111 %
b1111 '
b1111 -
b1111 .
1#
