probador.v
`timescale 1ns/1ns // escala de tiempo

/*Probador del registro de cuatro
   bits*/
module tester (
    output reg CLK,
    output reg ENB,
    output reg [1:0] MODO,
    output reg [3:0] D,
    input [3:0] Q,
    input RCO
);

/*Creacion del reloj, en este apartado de codigo se inicializa el reloj
donde este cambia cada segundo de tiempo, siendo 0 en uno y 1 en otro
y asi hasta terminar de correr las pruebas*/

always begin
    CLK = 1'b0; #1;
    CLK = 1'b1; #1;
end

// Ejecucion de pruebas

initial begin
    $display("Prueba #1: Desplazamiento a la izquierda");
    $display("ENB    MODO   D       Q    RCO");

    //primera instruccion 
    ENB = 1'b1; //activo el enable por que quiero que este empieza a cambiar
    MODO = 2'b11;
    D[3:0] = 4'b0000;

    //segunda y tercera instruccion
    /*Con esta se pretende enviar el flanco activo en CLK
    y establecer el MODO igual a  2'b00*/
    #1; #1;
    MODO = 2'b00; // Esta en 0000 para iniciar

    // se envian 4 flancos de reloj, en teoria el estado deberia ser 0001
    #1; #1;
    #1; #1;
    #1; #1;
    #1; #1;
    #1; #1;
    #1; #1;
    #1; #1;
    #1; #1;
    #1; #1;
    #1; #1;
    #1; #1;
    #1; #1;
    #1; #1;
    #1; #1;
    #1; #1;
    
    $finish;

end
endmodule

ff.v
/* flip flop tipo D de n bits disparado por flanco
   creciente de clk con entrada de habilitacion enb.
   */
module DFF_nbits_enb #(parameter BITS = 1)
(
    input clk,
    input enb,
    input [BITS-1:0] d,
    output reg [BITS-1:0] q
);

/* en cada flanco creciente se actualiza la salida
   q con el valor en d si la enb esta habilitado.
   */
always @(posedge clk) begin
    if (enb == 1'b1)
        q <= d;
end

endmodule

contador.v
`include "ff.v" //archivo de flipflop

module contador (
    input CLK,
    input ENB,
    input [1:0] MODO,
    input [3:0] D,
    output [3:0] Q,
    output RCO 
);

reg [3:0] d_In;
reg d_Out;



/* Utilizando las senales MODO[1:0] como de seleccion,
se determina el valor de d_In y d_Out, cada uno de los
casos contiene al numero de modo, siendo por ejemplo:
3'b00, refiriendose al MODO=00 donde en este caso ocurre Q+1, y
asi sucesivamente. 
*/
always @* begin
    case (MODO[1:0])
    //   caso         valor de RCO     valor de D[3:0]
        3'b00 : begin d_Out = 1'b1;  d_In = Q+1; end // CUENTA ASCENDENTE
        3'b01 : begin d_Out = 1'b0;  d_In = Q-1; end // CUENTA DESCENDENTE
        3'b10 : begin d_Out = 1'b0;  d_In = Q-3; end // CUENTA DE TRES EN TRES HACIA ABAJO
        3'b11 : begin d_Out = 1'b1;  d_In = D; end // CARGA EN PARALELO
        default: begin d_Out = d_Out; d_In = d_In;           end // no cambiar los valores en otro caso.
    endcase
end

/*En esta seccion de codigo nombramos los ff hechos, donde se nombran luego de
incluirr el archivo principal en la primera linea de codigo. Es importante mencionar
que se hace uso de una etiqueta el cual clasificara el proceso que se ejecuta
por lo que se veria de la siguiente manera: NOMBRE_MODULO etiqueta*/

/*Nota importante: .BITS(4), hace referencia a algo mencionado en el archivo ff.v,
donde a lo que hace referencia es a 4 bits.*/

DFF_nbits_enb #(.BITS(4)) DFF_4bits(.clk(CLK), .enb(ENB), .d(d_In[3:0]), .q(Q[3:0])); // Registro de 4bits para Q[3:0]
DFF_nbits_enb DFF_1bit(.clk(CLK), .enb(ENB), .d(d_Out), .q(RCO)); // Registro de 1bit para RCO

endmodule

testbench.v
`include "contador.v"
`include "probador.v"

/* banco de pruebas para el
   registro de cuatro bits
   y el probador
   */
module tb;
    wire clk, enb, RCO;
    wire [1:0] modo;
    wire [3:0] D; 
    wire [3:0] Q;

    contador DUT(.CLK(clk), .ENB(enb),
                      .MODO(modo[1:0]), .D(D[3:0]), .Q(Q[3:0]),
                      .RCO(RCO));

    /* se instancia un probador
       */
    tester test(.CLK(clk), .ENB(enb),
                .MODO(modo[1:0]), .D(D[3:0]), .Q(Q[3:0]),
                .RCO(RCO));

/* para generar las ondas y
    y visualizar en gtkwave
    */
    initial begin
        $dumpfile("testbench.vcd");
        $dumpvars;
    end


    /* para mostrar (vvp) los valores
    de las entradas y salidas
    del registro en cada flanco
    activo de reloj
    */
    always @(posedge clk) begin
        $display(" %b     %b     %b      %b   %b", enb, modo, D, Q, RCO);
    end

endmodule

testbench.vcd
$date
	Wed Aug 31 11:06:02 2022
$end
$version
	Icarus Verilog
$end
$timescale
	1ns
$end
$scope module tb $end
$var wire 2 ! modo [1:0] $end
$var wire 1 " enb $end
$var wire 1 # clk $end
$var wire 1 $ RCO $end
$var wire 4 % Q [3:0] $end
$var wire 4 & D [3:0] $end
$scope module DUT $end
$var wire 1 $ RCO $end
$var wire 4 ' Q [3:0] $end
$var wire 2 ( MODO [1:0] $end
$var wire 1 " ENB $end
$var wire 4 ) D [3:0] $end
$var wire 1 # CLK $end
$var reg 4 * d_In [3:0] $end
$var reg 1 + d_Out $end
$scope module DFF_1bit $end
$var wire 1 + d $end
$var wire 1 " enb $end
$var wire 1 # clk $end
$var reg 1 $ q $end
$upscope $end
$scope module DFF_4bits $end
$var wire 4 , d [3:0] $end
$var wire 1 " enb $end
$var wire 1 # clk $end
$var reg 4 - q [3:0] $end
$upscope $end
$upscope $end
$scope module test $end
$var wire 4 . Q [3:0] $end
$var wire 1 $ RCO $end
$var reg 1 # CLK $end
$var reg 4 / D [3:0] $end
$var reg 1 " ENB $end
$var reg 2 0 MODO [1:0] $end
$upscope $end
$upscope $end
$enddefinitions $end
#0
$dumpvars
b11 0
b0 /
bx .
bx -
b0 ,
1+
b0 *
b0 )
b11 (
bx '
b0 &
bx %
x$
0#
1"
b11 !
$end
#1
b0 %
b0 '
b0 -
b0 .
1$
1#
#2
b1 *
b1 ,
0+
b0 !
b0 (
b0 0
0#
#3
b10 *
b10 ,
0$
b1 %
b1 '
b1 -
b1 .
1#
#4
0#
#5
b11 *
b11 ,
b10 %
b10 '
b10 -
b10 .
1#
#6
0#
#7
b100 *
b100 ,
b11 %
b11 '
b11 -
b11 .
1#
#8
0#
#9
b101 *
b101 ,
b100 %
b100 '
b100 -
b100 .
1#
#10
0#
#11
b110 *
b110 ,
b101 %
b101 '
b101 -
b101 .
1#
#12
0#
#13
b111 *
b111 ,
b110 %
b110 '
b110 -
b110 .
1#
#14
0#
#15
b1000 *
b1000 ,
b111 %
b111 '
b111 -
b111 .
1#
#16
0#
#17
b1001 *
b1001 ,
b1000 %
b1000 '
b1000 -
b1000 .
1#
#18
0#
#19
b1010 *
b1010 ,
b1001 %
b1001 '
b1001 -
b1001 .
1#
#20
0#
#21
b1011 *
b1011 ,
b1010 %
b1010 '
b1010 -
b1010 .
1#
#22
0#
#23
b1100 *
b1100 ,
b1011 %
b1011 '
b1011 -
b1011 .
1#
#24
0#
#25
b1101 *
b1101 ,
b1100 %
b1100 '
b1100 -
b1100 .
1#
#26
0#
#27
b1110 *
b1110 ,
b1101 %
b1101 '
b1101 -
b1101 .
1#
#28
0#
#29
b1111 *
b1111 ,
b1110 %
b1110 '
b1110 -
b1110 .
1#
#30
0#
#31
b0 *
b0 ,
b1111 %
b1111 '
b1111 -
b1111 .
1#
