Tarea4/tester.v
module tester (
    input SCL,
    input SDA_OUT,
    input SDA_OE,
    input [15:0] RD_DATA,
    output reg START_STB,
    output reg [15:0] WR_DATA,
    output reg [6:0]I2C_ADDR,
    output reg CLK,
    output reg RST,
    output reg RNW,
    output reg SDA_IN
);


always begin
    CLK = 0; #1;
    CLK = 1; #1;

end

initial begin
    // Prueba 1: reiniciar los registros y salidas
    RST = 0; #1; #1; 
    #1; #1; #1;
    RST = 0; #1; #1;
end

// Instrucciones para el generador de transacciones

initial begin

  
     // Initialize RST
    RST = 0;
    WR_DATA = 0;
    I2C_ADDR = 0;
    RNW = 0;
    SDA_IN = 0;
    START_STB = 0;
    #8;

    // prueba de escritura
    RST = 1;
    START_STB = 1;
    #2; 
    START_STB = 0;
    I2C_ADDR = 7'b1010010;
    #80;
    RNW = 0; 
    #2; 
    WR_DATA = 15'b101010111010111;
    #500;

    // reinicio de pruebas
    RST = 1'b0;
    START_STB = 1'b0;
    I2C_ADDR = 7'b0000000;
    #8;

    // prueba de lectura
    RST = 1;
    START_STB = 1;
    #2;
    START_STB = 0;
    I2C_ADDR = 7'b1010010;
    RNW = 1;
    #100;  
    //RNW = 1;
    #2;

    SDA_IN = 1; #32;
    SDA_IN = 1; #32;
    SDA_IN = 1; #32;
    SDA_IN = 1; #32;
    SDA_IN = 0; #32;
    SDA_IN = 0; #32;
    SDA_IN = 1; #32;
    SDA_IN = 1; #32;
    SDA_IN = 0; #32;
    SDA_IN = 0; #32;
    SDA_IN = 1; #32;
    SDA_IN = 0; #32;
    SDA_IN = 1; #32;
    SDA_IN = 1; #32;
    SDA_IN = 0; #32;
    SDA_IN = 1; #32;
    SDA_IN = 0; #32;

    #1000;
    $finish;
end

endmodule

Tarea4/I2C.v
module I2C 
(
    input CLK                   ,
    input RST                 , 
    input START_STB             ,
    input RNW                   ,
    input SDA_IN                ,
    input [6:0]I2C_ADDR         ,
    input [15:0]WR_DATA         , 
    output SCL                  , 
    output reg SDA_OUT          ,  
    output reg SDA_OE           , 
    output reg [15:0]RD_DATA
);
    
    reg [3:0] estado;
    reg [15:0] guardar;

    reg [6:0] contador;
    reg [15:0] cuenta;
    reg RW;
    reg [15:0] bits_rddata; // agarra lo que este en los primeros 7 bits del RD_DATA para poder hacer la conversion
    reg [7:0] read_cnt; // cambiar nombre




    reg [3:0] RESULT = 0;
    always@(posedge CLK) begin
        RESULT = RESULT + 1'b1;
    end
    assign SCL = RESULT[2];

    // RST = 0, registros = 0
    always @(posedge CLK) begin
        if (~RST) begin
            RD_DATA <= 0;
            SDA_OUT <= 0;
            SDA_OE <= 0;
            estado <= 0;
            contador <= 0;
            cuenta <= 16'd16;
        end
    end

    always @(posedge SCL)begin

        if (RST) begin


                //IDLE
            if (estado == 4'b0000)begin
                SDA_OUT <= 0;
                estado <= 4'b0001; 
                SDA_OE <= 0;
            end

                //START
            if (estado == 4'b0001) begin
                estado <= 4'b0010;
                contador <= 6;    
                SDA_OE <= 0;     // Este contador leer el MSB del I2C_ADDR
                SDA_OUT <= 1;
            end

                //SLAVE
            if (estado == 4'b0010)begin
                
                estado <= 4'b0010;
                SDA_OUT <= I2C_ADDR[contador];
                SDA_OE <= 1;

                if (contador == 0) begin
                    estado <= 4'b0011;
                end else begin
                    contador <= contador - 1;
                end
            end

                //RNW
            if (estado == 4'b0011)begin
                SDA_OE <= 0;
                SDA_OUT <= RNW;
                estado <= 4'b0100;
            end

                //ACK
            if (estado == 4'b0100) begin
                RW = RNW;
                if (RW == 0)begin   // Modo de Escritura
                    estado <= 4'b0101; 
                    cuenta <= 7;
                    bits_rddata <= WR_DATA[15:8];
                    SDA_OUT = 1;
 
              
                end else if (RW == 1) begin  // Modo de Lectura
                    estado <= 4'b0110;
                    cuenta <= 7;
                    guardar[15:0] <= RD_DATA[15:0];
                    SDA_OUT = 1;


                end
            end

                //WRITE
            if (estado == 4'b0101) begin
                SDA_OUT <= bits_rddata[cuenta];
                

                if (cuenta == 0) begin
                    estado <= 4'b0111;
                end else begin
                    cuenta <= cuenta - 1;
                end

            end

                //READ
            if (estado == 4'b0110) begin

                RD_DATA[cuenta] <= SDA_IN;  
                SDA_OUT <= RD_DATA[cuenta];
                if (cuenta == 0) begin
                    estado <= 4'b1000;
                end else begin
                    cuenta <= cuenta - 1;
                end

            end

                //ACK WRITE
            if (estado == 4'b0111) begin
                SDA_OUT <= 1;
                SDA_OE <= 0;
                estado <= 4'b1001;
                bits_rddata <= WR_DATA[7:0];
                cuenta <= 7;
            end

                //ACK READ
            if (estado == 4'b1000) begin
                SDA_OUT <= 0;
                SDA_OE <= 0;
                estado <= 4'b1010;
                read_cnt <= 7;
            end

                //ME COMPLETA LOS OTROS BITS DEL ACKNOLEDGE WRITE
            if(estado == 4'b1001) begin
                SDA_OUT <= bits_rddata[cuenta];
                SDA_OE <= 1;

                if (cuenta == 0) begin
                    estado <= 4'b1011;
                end else begin
                    cuenta <= cuenta - 1;
                end
            end

                //ME COMPLETA LOS OTROS BITS DEL ACK READ
            if (estado == 4'b1010) begin
                RD_DATA[read_cnt] <= SDA_IN;
                SDA_OUT <= guardar[read_cnt];

                if (read_cnt == 0) begin
                    estado <= 4'b1011;
                end else begin
                    read_cnt <= read_cnt - 1;
                end
            end

                //~ACK
            if (estado == 4'b1011) begin
                SDA_OUT <= 0;
                estado <= 4'b1111;
            end

                //CONDICION DE PARADA
            if (estado == 4'b1111) begin
                SDA_OUT <= 1;
                estado <= 4'b0000;
            end 

        end


    end

endmodule

Tarea4/testbench.v
`include "I2C.v"
`include "tester.v"

module testbench();

    wire SCL;
    wire SDA_OE;
    wire SDA_OUT;
    wire [15:0] RD_DATA;
    wire [15:0] WR_DATA;
    wire START_STB;
    wire [6:0]I2C_ADDR;
    wire CLK;
    wire RST;
    wire SDA_IN;
    wire RNW;

        I2C DUT(.SCL(SCL), 
                    .SDA_OE(SDA_OE), 
                    .SDA_OUT(SDA_OUT), 
                    .RD_DATA(RD_DATA), 
                    .WR_DATA(WR_DATA), 
                    .START_STB(START_STB), 
                    .I2C_ADDR(I2C_ADDR), 
                    .RNW(RNW), 
                    .CLK(CLK), 
                    .RST(RST), 
                    .SDA_IN(SDA_IN));

    tester TESTER (.SCL(SCL), 
                    .SDA_OE(SDA_OE), 
                    .SDA_OUT(SDA_OUT), 
                    .RD_DATA(RD_DATA),
                    .WR_DATA(WR_DATA), 
                    .START_STB(START_STB), 
                    .I2C_ADDR(I2C_ADDR), 
                    .RNW(RNW), 
                    .CLK(CLK), 
                    .RST(RST), 
                    .SDA_IN(SDA_IN));

    initial begin
        $dumpfile("testbench.vcd");
        $dumpvars;
    end


endmodule

Tarea4/testbench.vcd
$date
	Mon Oct 24 21:11:41 2022
$end
$version
	Icarus Verilog
$end
$timescale
	1s
$end
$scope module testbench $end
$var wire 16 ! WR_DATA [15:0] $end
$var wire 1 " START_STB $end
$var wire 1 # SDA_OUT $end
$var wire 1 $ SDA_OE $end
$var wire 1 % SDA_IN $end
$var wire 1 & SCL $end
$var wire 1 ' RST $end
$var wire 1 ( RNW $end
$var wire 16 ) RD_DATA [15:0] $end
$var wire 7 * I2C_ADDR [6:0] $end
$var wire 1 + CLK $end
$scope module DUT $end
$var wire 16 , WR_DATA [15:0] $end
$var wire 1 " START_STB $end
$var wire 1 % SDA_IN $end
$var wire 1 & SCL $end
$var wire 1 ' RST $end
$var wire 1 ( RNW $end
$var wire 7 - I2C_ADDR [6:0] $end
$var wire 1 + CLK $end
$var reg 16 . RD_DATA [15:0] $end
$var reg 4 / RESULT [3:0] $end
$var reg 1 0 RW $end
$var reg 1 $ SDA_OE $end
$var reg 1 # SDA_OUT $end
$var reg 16 1 bits_rddata [15:0] $end
$var reg 7 2 contador [6:0] $end
$var reg 16 3 cuenta [15:0] $end
$var reg 4 4 estado [3:0] $end
$var reg 16 5 guardar [15:0] $end
$var reg 8 6 read_cnt [7:0] $end
$upscope $end
$scope module TESTER $end
$var wire 16 7 RD_DATA [15:0] $end
$var wire 1 & SCL $end
$var wire 1 $ SDA_OE $end
$var wire 1 # SDA_OUT $end
$var reg 1 + CLK $end
$var reg 7 8 I2C_ADDR [6:0] $end
$var reg 1 ( RNW $end
$var reg 1 ' RST $end
$var reg 1 % SDA_IN $end
$var reg 1 " START_STB $end
$var reg 16 9 WR_DATA [15:0] $end
$upscope $end
$upscope $end
$enddefinitions $end
#0
$dumpvars
b0 9
b0 8
bx 7
bx 6
bx 5
bx 4
bx 3
bx 2
bx 1
x0
b0 /
bx .
b0 -
b0 ,
0+
b0 *
bx )
0(
0'
0&
0%
x$
x#
0"
b0 !
$end
#1
b10000 3
b0 2
b0 4
0$
0#
b0 )
b0 .
b0 7
b1 /
1+
#2
0+
#3
b10 /
1+
#4
0+
#5
b11 /
1+
#6
0+
#7
1&
b100 /
1+
#8
0+
1"
1'
#9
b101 /
1+
#10
0+
b1010010 *
b1010010 -
b1010010 8
0"
#11
b110 /
1+
#12
0+
#13
b111 /
1+
#14
0+
#15
0&
b1000 /
1+
#16
0+
#17
b1001 /
1+
#18
0+
#19
b1010 /
1+
#20
0+
#21
b1011 /
1+
#22
0+
#23
b1 4
1&
b1100 /
1+
#24
0+
#25
b1101 /
1+
#26
0+
#27
b1110 /
1+
#28
0+
#29
b1111 /
1+
#30
0+
#31
0&
b0 /
1+
#32
0+
#33
b1 /
1+
#34
0+
#35
b10 /
1+
#36
0+
#37
b11 /
1+
#38
0+
#39
1#
b110 2
b10 4
1&
b100 /
1+
#40
0+
#41
b101 /
1+
#42
0+
#43
b110 /
1+
#44
0+
#45
b111 /
1+
#46
0+
#47
0&
b1000 /
1+
#48
0+
#49
b1001 /
1+
#50
0+
#51
b1010 /
1+
#52
0+
#53
b1011 /
1+
#54
0+
#55
b101 2
1$
1&
b1100 /
1+
#56
0+
#57
b1101 /
1+
#58
0+
#59
b1110 /
1+
#60
0+
#61
b1111 /
1+
#62
0+
#63
0&
b0 /
1+
#64
0+
#65
b1 /
1+
#66
0+
#67
b10 /
1+
#68
0+
#69
b11 /
1+
#70
0+
#71
b100 2
0#
1&
b100 /
1+
#72
0+
#73
b101 /
1+
#74
0+
#75
b110 /
1+
#76
0+
#77
b111 /
1+
#78
0+
#79
0&
b1000 /
1+
#80
0+
#81
b1001 /
1+
#82
0+
#83
b1010 /
1+
#84
0+
#85
b1011 /
1+
#86
0+
#87
b11 2
1#
1&
b1100 /
1+
#88
0+
#89
b1101 /
1+
#90
0+
#91
b1110 /
1+
#92
0+
b101010111010111 !
b101010111010111 ,
b101010111010111 9
#93
b1111 /
1+
#94
0+
#95
0&
b0 /
1+
#96
0+
#97
b1 /
1+
#98
0+
#99
b10 /
1+
#100
0+
#101
b11 /
1+
#102
0+
#103
b10 2
0#
1&
b100 /
1+
#104
0+
#105
b101 /
1+
#106
0+
#107
b110 /
1+
#108
0+
#109
b111 /
1+
#110
0+
#111
0&
b1000 /
1+
#112
0+
#113
b1001 /
1+
#114
0+
#115
b1010 /
1+
#116
0+
#117
b1011 /
1+
#118
0+
#119
b1 2
1&
b1100 /
1+
#120
0+
#121
b1101 /
1+
#122
0+
#123
b1110 /
1+
#124
0+
#125
b1111 /
1+
#126
0+
#127
0&
b0 /
1+
#128
0+
#129
b1 /
1+
#130
0+
#131
b10 /
1+
#132
0+
#133
b11 /
1+
#134
0+
#135
b0 2
1#
1&
b100 /
1+
#136
0+
#137
b101 /
1+
#138
0+
#139
b110 /
1+
#140
0+
#141
b111 /
1+
#142
0+
#143
0&
b1000 /
1+
#144
0+
#145
b1001 /
1+
#146
0+
#147
b1010 /
1+
#148
0+
#149
b1011 /
1+
#150
0+
#151
b11 4
0#
1&
b1100 /
1+
#152
0+
#153
b1101 /
1+
#154
0+
#155
b1110 /
1+
#156
0+
#157
b1111 /
1+
#158
0+
#159
0&
b0 /
1+
#160
0+
#161
b1 /
1+
#162
0+
#163
b10 /
1+
#164
0+
#165
b11 /
1+
#166
0+
#167
b100 4
0$
1&
b100 /
1+
#168
0+
#169
b101 /
1+
#170
0+
#171
b110 /
1+
#172
0+
#173
b111 /
1+
#174
0+
#175
0&
b1000 /
1+
#176
0+
#177
b1001 /
1+
#178
0+
#179
b1010 /
1+
#180
0+
#181
b1011 /
1+
#182
0+
#183
b1010101 1
b111 3
b101 4
1#
00
1&
b1100 /
1+
#184
0+
#185
b1101 /
1+
#186
0+
#187
b1110 /
1+
#188
0+
#189
b1111 /
1+
#190
0+
#191
0&
b0 /
1+
#192
0+
#193
b1 /
1+
#194
0+
#195
b10 /
1+
#196
0+
#197
b11 /
1+
#198
0+
#199
b110 3
0#
1&
b100 /
1+
#200
0+
#201
b101 /
1+
#202
0+
#203
b110 /
1+
#204
0+
#205
b111 /
1+
#206
0+
#207
0&
b1000 /
1+
#208
0+
#209
b1001 /
1+
#210
0+
#211
b1010 /
1+
#212
0+
#213
b1011 /
1+
#214
0+
#215
b101 3
1#
1&
b1100 /
1+
#216
0+
#217
b1101 /
1+
#218
0+
#219
b1110 /
1+
#220
0+
#221
b1111 /
1+
#222
0+
#223
0&
b0 /
1+
#224
0+
#225
b1 /
1+
#226
0+
#227
b10 /
1+
#228
0+
#229
b11 /
1+
#230
0+
#231
b100 3
0#
1&
b100 /
1+
#232
0+
#233
b101 /
1+
#234
0+
#235
b110 /
1+
#236
0+
#237
b111 /
1+
#238
0+
#239
0&
b1000 /
1+
#240
0+
#241
b1001 /
1+
#242
0+
#243
b1010 /
1+
#244
0+
#245
b1011 /
1+
#246
0+
#247
b11 3
1#
1&
b1100 /
1+
#248
0+
#249
b1101 /
1+
#250
0+
#251
b1110 /
1+
#252
0+
#253
b1111 /
1+
#254
0+
#255
0&
b0 /
1+
#256
0+
#257
b1 /
1+
#258
0+
#259
b10 /
1+
#260
0+
#261
b11 /
1+
#262
0+
#263
b10 3
0#
1&
b100 /
1+
#264
0+
#265
b101 /
1+
#266
0+
#267
b110 /
1+
#268
0+
#269
b111 /
1+
#270
0+
#271
0&
b1000 /
1+
#272
0+
#273
b1001 /
1+
#274
0+
#275
b1010 /
1+
#276
0+
#277
b1011 /
1+
#278
0+
#279
b1 3
1#
1&
b1100 /
1+
#280
0+
#281
b1101 /
1+
#282
0+
#283
b1110 /
1+
#284
0+
#285
b1111 /
1+
#286
0+
#287
0&
b0 /
1+
#288
0+
#289
b1 /
1+
#290
0+
#291
b10 /
1+
#292
0+
#293
b11 /
1+
#294
0+
#295
b0 3
0#
1&
b100 /
1+
#296
0+
#297
b101 /
1+
#298
0+
#299
b110 /
1+
#300
0+
#301
b111 /
1+
#302
0+
#303
0&
b1000 /
1+
#304
0+
#305
b1001 /
1+
#306
0+
#307
b1010 /
1+
#308
0+
#309
b1011 /
1+
#310
0+
#311
b111 4
1#
1&
b1100 /
1+
#312
0+
#313
b1101 /
1+
#314
0+
#315
b1110 /
1+
#316
0+
#317
b1111 /
1+
#318
0+
#319
0&
b0 /
1+
#320
0+
#321
b1 /
1+
#322
0+
#323
b10 /
1+
#324
0+
#325
b11 /
1+
#326
0+
#327
b111 3
b11010111 1
b1001 4
1&
b100 /
1+
#328
0+
#329
b101 /
1+
#330
0+
#331
b110 /
1+
#332
0+
#333
b111 /
1+
#334
0+
#335
0&
b1000 /
1+
#336
0+
#337
b1001 /
1+
#338
0+
#339
b1010 /
1+
#340
0+
#341
b1011 /
1+
#342
0+
#343
b110 3
1$
1&
b1100 /
1+
#344
0+
#345
b1101 /
1+
#346
0+
#347
b1110 /
1+
#348
0+
#349
b1111 /
1+
#350
0+
#351
0&
b0 /
1+
#352
0+
#353
b1 /
1+
#354
0+
#355
b10 /
1+
#356
0+
#357
b11 /
1+
#358
0+
#359
b101 3
1&
b100 /
1+
#360
0+
#361
b101 /
1+
#362
0+
#363
b110 /
1+
#364
0+
#365
b111 /
1+
#366
0+
#367
0&
b1000 /
1+
#368
0+
#369
b1001 /
1+
#370
0+
#371
b1010 /
1+
#372
0+
#373
b1011 /
1+
#374
0+
#375
b100 3
0#
1&
b1100 /
1+
#376
0+
#377
b1101 /
1+
#378
0+
#379
b1110 /
1+
#380
0+
#381
b1111 /
1+
#382
0+
#383
0&
b0 /
1+
#384
0+
#385
b1 /
1+
#386
0+
#387
b10 /
1+
#388
0+
#389
b11 /
1+
#390
0+
#391
b11 3
1#
1&
b100 /
1+
#392
0+
#393
b101 /
1+
#394
0+
#395
b110 /
1+
#396
0+
#397
b111 /
1+
#398
0+
#399
0&
b1000 /
1+
#400
0+
#401
b1001 /
1+
#402
0+
#403
b1010 /
1+
#404
0+
#405
b1011 /
1+
#406
0+
#407
b10 3
0#
1&
b1100 /
1+
#408
0+
#409
b1101 /
1+
#410
0+
#411
b1110 /
1+
#412
0+
#413
b1111 /
1+
#414
0+
#415
0&
b0 /
1+
#416
0+
#417
b1 /
1+
#418
0+
#419
b10 /
1+
#420
0+
#421
b11 /
1+
#422
0+
#423
b1 3
1#
1&
b100 /
1+
#424
0+
#425
b101 /
1+
#426
0+
#427
b110 /
1+
#428
0+
#429
b111 /
1+
#430
0+
#431
0&
b1000 /
1+
#432
0+
#433
b1001 /
1+
#434
0+
#435
b1010 /
1+
#436
0+
#437
b1011 /
1+
#438
0+
#439
b0 3
1&
b1100 /
1+
#440
0+
#441
b1101 /
1+
#442
0+
#443
b1110 /
1+
#444
0+
#445
b1111 /
1+
#446
0+
#447
0&
b0 /
1+
#448
0+
#449
b1 /
1+
#450
0+
#451
b10 /
1+
#452
0+
#453
b11 /
1+
#454
0+
#455
b1011 4
1&
b100 /
1+
#456
0+
#457
b101 /
1+
#458
0+
#459
b110 /
1+
#460
0+
#461
b111 /
1+
#462
0+
#463
0&
b1000 /
1+
#464
0+
#465
b1001 /
1+
#466
0+
#467
b1010 /
1+
#468
0+
#469
b1011 /
1+
#470
0+
#471
b1111 4
0#
1&
b1100 /
1+
#472
0+
#473
b1101 /
1+
#474
0+
#475
b1110 /
1+
#476
0+
#477
b1111 /
1+
#478
0+
#479
0&
b0 /
1+
#480
0+
#481
b1 /
1+
#482
0+
#483
b10 /
1+
#484
0+
#485
b11 /
1+
#486
0+
#487
b0 4
1#
1&
b100 /
1+
#488
0+
#489
b101 /
1+
#490
0+
#491
b110 /
1+
#492
0+
#493
b111 /
1+
#494
0+
#495
0&
b1000 /
1+
#496
0+
#497
b1001 /
1+
#498
0+
#499
b1010 /
1+
#500
0+
#501
b1011 /
1+
#502
0+
#503
0$
b1 4
0#
1&
b1100 /
1+
#504
0+
#505
b1101 /
1+
#506
0+
#507
b1110 /
1+
#508
0+
#509
b1111 /
1+
#510
0+
#511
0&
b0 /
1+
#512
0+
#513
b1 /
1+
#514
0+
#515
b10 /
1+
#516
0+
#517
b11 /
1+
#518
0+
#519
1#
b110 2
b10 4
1&
b100 /
1+
#520
0+
#521
b101 /
1+
#522
0+
#523
b110 /
1+
#524
0+
#525
b111 /
1+
#526
0+
#527
0&
b1000 /
1+
#528
0+
#529
b1001 /
1+
#530
0+
#531
b1010 /
1+
#532
0+
#533
b1011 /
1+
#534
0+
#535
b101 2
1$
1&
b1100 /
1+
#536
0+
#537
b1101 /
1+
#538
0+
#539
b1110 /
1+
#540
0+
#541
b1111 /
1+
#542
0+
#543
0&
b0 /
1+
#544
0+
#545
b1 /
1+
#546
0+
#547
b10 /
1+
#548
0+
#549
b11 /
1+
#550
0+
#551
b100 2
0#
1&
b100 /
1+
#552
0+
#553
b101 /
1+
#554
0+
#555
b110 /
1+
#556
0+
#557
b111 /
1+
#558
0+
#559
0&
b1000 /
1+
#560
0+
#561
b1001 /
1+
#562
0+
#563
b1010 /
1+
#564
0+
#565
b1011 /
1+
#566
0+
#567
b11 2
1#
1&
b1100 /
1+
#568
0+
#569
b1101 /
1+
#570
0+
#571
b1110 /
1+
#572
0+
#573
b1111 /
1+
#574
0+
#575
0&
b0 /
1+
#576
0+
#577
b1 /
1+
#578
0+
#579
b10 /
1+
#580
0+
#581
b11 /
1+
#582
0+
#583
b10 2
0#
1&
b100 /
1+
#584
0+
#585
b101 /
1+
#586
0+
#587
b110 /
1+
#588
0+
#589
b111 /
1+
#590
0+
#591
0&
b1000 /
1+
#592
0+
b0 *
b0 -
b0 8
0'
#593
b10000 3
b0 2
b0 4
0$
b1001 /
1+
#594
0+
#595
b1010 /
1+
#596
0+
#597
b1011 /
1+
#598
0+
#599
1&
b1100 /
1+
#600
0+
1"
1'
#601
b1101 /
1+
#602
0+
1(
b1010010 *
b1010010 -
b1010010 8
0"
#603
b1110 /
1+
#604
0+
#605
b1111 /
1+
#606
0+
#607
0&
b0 /
1+
#608
0+
#609
b1 /
1+
#610
0+
#611
b10 /
1+
#612
0+
#613
b11 /
1+
#614
0+
#615
b1 4
1&
b100 /
1+
#616
0+
#617
b101 /
1+
#618
0+
#619
b110 /
1+
#620
0+
#621
b111 /
1+
#622
0+
#623
0&
b1000 /
1+
#624
0+
#625
b1001 /
1+
#626
0+
#627
b1010 /
1+
#628
0+
#629
b1011 /
1+
#630
0+
#631
1#
b110 2
b10 4
1&
b1100 /
1+
#632
0+
#633
b1101 /
1+
#634
0+
#635
b1110 /
1+
#636
0+
#637
b1111 /
1+
#638
0+
#639
0&
b0 /
1+
#640
0+
#641
b1 /
1+
#642
0+
#643
b10 /
1+
#644
0+
#645
b11 /
1+
#646
0+
#647
b101 2
1$
1&
b100 /
1+
#648
0+
#649
b101 /
1+
#650
0+
#651
b110 /
1+
#652
0+
#653
b111 /
1+
#654
0+
#655
0&
b1000 /
1+
#656
0+
#657
b1001 /
1+
#658
0+
#659
b1010 /
1+
#660
0+
#661
b1011 /
1+
#662
0+
#663
b100 2
0#
1&
b1100 /
1+
#664
0+
#665
b1101 /
1+
#666
0+
#667
b1110 /
1+
#668
0+
#669
b1111 /
1+
#670
0+
#671
0&
b0 /
1+
#672
0+
#673
b1 /
1+
#674
0+
#675
b10 /
1+
#676
0+
#677
b11 /
1+
#678
0+
#679
b11 2
1#
1&
b100 /
1+
#680
0+
#681
b101 /
1+
#682
0+
#683
b110 /
1+
#684
0+
#685
b111 /
1+
#686
0+
#687
0&
b1000 /
1+
#688
0+
#689
b1001 /
1+
#690
0+
#691
b1010 /
1+
#692
0+
#693
b1011 /
1+
#694
0+
#695
b10 2
0#
1&
b1100 /
1+
#696
0+
#697
b1101 /
1+
#698
0+
#699
b1110 /
1+
#700
0+
#701
b1111 /
1+
#702
0+
#703
0&
b0 /
1+
#704
0+
1%
#705
b1 /
1+
#706
0+
#707
b10 /
1+
#708
0+
#709
b11 /
1+
#710
0+
#711
b1 2
1&
b100 /
1+
#712
0+
#713
b101 /
1+
#714
0+
#715
b110 /
1+
#716
0+
#717
b111 /
1+
#718
0+
#719
0&
b1000 /
1+
#720
0+
#721
b1001 /
1+
#722
0+
#723
b1010 /
1+
#724
0+
#725
b1011 /
1+
#726
0+
#727
b0 2
1#
1&
b1100 /
1+
#728
0+
#729
b1101 /
1+
#730
0+
#731
b1110 /
1+
#732
0+
#733
b1111 /
1+
#734
0+
#735
0&
b0 /
1+
#736
0+
#737
b1 /
1+
#738
0+
#739
b10 /
1+
#740
0+
#741
b11 /
1+
#742
0+
#743
b11 4
0#
1&
b100 /
1+
#744
0+
#745
b101 /
1+
#746
0+
#747
b110 /
1+
#748
0+
#749
b111 /
1+
#750
0+
#751
0&
b1000 /
1+
#752
0+
#753
b1001 /
1+
#754
0+
#755
b1010 /
1+
#756
0+
#757
b1011 /
1+
#758
0+
#759
b100 4
1#
0$
1&
b1100 /
1+
#760
0+
#761
b1101 /
1+
#762
0+
#763
b1110 /
1+
#764
0+
#765
b1111 /
1+
#766
0+
#767
0&
b0 /
1+
#768
0+
#769
b1 /
1+
#770
0+
#771
b10 /
1+
#772
0+
#773
b11 /
1+
#774
0+
#775
b0 5
b111 3
b110 4
10
1&
b100 /
1+
#776
0+
#777
b101 /
1+
#778
0+
#779
b110 /
1+
#780
0+
#781
b111 /
1+
#782
0+
#783
0&
b1000 /
1+
#784
0+
#785
b1001 /
1+
#786
0+
#787
b1010 /
1+
#788
0+
#789
b1011 /
1+
#790
0+
#791
b110 3
0#
b10000000 )
b10000000 .
b10000000 7
1&
b1100 /
1+
#792
0+
#793
b1101 /
1+
#794
0+
#795
b1110 /
1+
#796
0+
#797
b1111 /
1+
#798
0+
#799
0&
b0 /
1+
#800
0+
#801
b1 /
1+
#802
0+
#803
b10 /
1+
#804
0+
#805
b11 /
1+
#806
0+
#807
b101 3
b11000000 )
b11000000 .
b11000000 7
1&
b100 /
1+
#808
0+
#809
b101 /
1+
#810
0+
#811
b110 /
1+
#812
0+
#813
b111 /
1+
#814
0+
#815
0&
b1000 /
1+
#816
0+
#817
b1001 /
1+
#818
0+
#819
b1010 /
1+
#820
0+
#821
b1011 /
1+
#822
0+
#823
b100 3
b11100000 )
b11100000 .
b11100000 7
1&
b1100 /
1+
#824
0+
#825
b1101 /
1+
#826
0+
#827
b1110 /
1+
#828
0+
#829
b1111 /
1+
#830
0+
#831
0&
b0 /
1+
#832
0+
0%
#833
b1 /
1+
#834
0+
#835
b10 /
1+
#836
0+
#837
b11 /
1+
#838
0+
#839
b11 3
1&
b100 /
1+
#840
0+
#841
b101 /
1+
#842
0+
#843
b110 /
1+
#844
0+
#845
b111 /
1+
#846
0+
#847
0&
b1000 /
1+
#848
0+
#849
b1001 /
1+
#850
0+
#851
b1010 /
1+
#852
0+
#853
b1011 /
1+
#854
0+
#855
b10 3
1&
b1100 /
1+
#856
0+
#857
b1101 /
1+
#858
0+
#859
b1110 /
1+
#860
0+
#861
b1111 /
1+
#862
0+
#863
0&
b0 /
1+
#864
0+
#865
b1 /
1+
#866
0+
#867
b10 /
1+
#868
0+
#869
b11 /
1+
#870
0+
#871
b1 3
1&
b100 /
1+
#872
0+
#873
b101 /
1+
#874
0+
#875
b110 /
1+
#876
0+
#877
b111 /
1+
#878
0+
#879
0&
b1000 /
1+
#880
0+
#881
b1001 /
1+
#882
0+
#883
b1010 /
1+
#884
0+
#885
b1011 /
1+
#886
0+
#887
b0 3
1&
b1100 /
1+
#888
0+
#889
b1101 /
1+
#890
0+
#891
b1110 /
1+
#892
0+
#893
b1111 /
1+
#894
0+
#895
0&
b0 /
1+
#896
0+
1%
#897
b1 /
1+
#898
0+
#899
b10 /
1+
#900
0+
#901
b11 /
1+
#902
0+
#903
b1000 4
b11100001 )
b11100001 .
b11100001 7
1&
b100 /
1+
#904
0+
#905
b101 /
1+
#906
0+
#907
b110 /
1+
#908
0+
#909
b111 /
1+
#910
0+
#911
0&
b1000 /
1+
#912
0+
#913
b1001 /
1+
#914
0+
#915
b1010 /
1+
#916
0+
#917
b1011 /
1+
#918
0+
#919
b111 6
b1010 4
1&
b1100 /
1+
#920
0+
#921
b1101 /
1+
#922
0+
#923
b1110 /
1+
#924
0+
#925
b1111 /
1+
#926
0+
#927
0&
b0 /
1+
#928
0+
#929
b1 /
1+
#930
0+
#931
b10 /
1+
#932
0+
#933
b11 /
1+
#934
0+
#935
b110 6
1&
b100 /
1+
#936
0+
#937
b101 /
1+
#938
0+
#939
b110 /
1+
#940
0+
#941
b111 /
1+
#942
0+
#943
0&
b1000 /
1+
#944
0+
#945
b1001 /
1+
#946
0+
#947
b1010 /
1+
#948
0+
#949
b1011 /
1+
#950
0+
#951
b101 6
1&
b1100 /
1+
#952
0+
#953
b1101 /
1+
#954
0+
#955
b1110 /
1+
#956
0+
#957
b1111 /
1+
#958
0+
#959
0&
b0 /
1+
#960
0+
0%
#961
b1 /
1+
#962
0+
#963
b10 /
1+
#964
0+
#965
b11 /
1+
#966
0+
#967
b100 6
b11000001 )
b11000001 .
b11000001 7
1&
b100 /
1+
#968
0+
#969
b101 /
1+
#970
0+
#971
b110 /
1+
#972
0+
#973
b111 /
1+
#974
0+
#975
0&
b1000 /
1+
#976
0+
#977
b1001 /
1+
#978
0+
#979
b1010 /
1+
#980
0+
#981
b1011 /
1+
#982
0+
#983
b11 6
1&
b1100 /
1+
#984
0+
#985
b1101 /
1+
#986
0+
#987
b1110 /
1+
#988
0+
#989
b1111 /
1+
#990
0+
#991
0&
b0 /
1+
#992
0+
#993
b1 /
1+
#994
0+
#995
b10 /
1+
#996
0+
#997
b11 /
1+
#998
0+
#999
b10 6
1&
b100 /
1+
#1000
0+
#1001
b101 /
1+
#1002
0+
#1003
b110 /
1+
#1004
0+
#1005
b111 /
1+
#1006
0+
#1007
0&
b1000 /
1+
#1008
0+
#1009
b1001 /
1+
#1010
0+
#1011
b1010 /
1+
#1012
0+
#1013
b1011 /
1+
#1014
0+
#1015
b1 6
1&
b1100 /
1+
#1016
0+
#1017
b1101 /
1+
#1018
0+
#1019
b1110 /
1+
#1020
0+
#1021
b1111 /
1+
#1022
0+
#1023
0&
b0 /
1+
#1024
0+
1%
#1025
b1 /
1+
#1026
0+
#1027
b10 /
1+
#1028
0+
#1029
b11 /
1+
#1030
0+
#1031
b0 6
b11000011 )
b11000011 .
b11000011 7
1&
b100 /
1+
#1032
0+
#1033
b101 /
1+
#1034
0+
#1035
b110 /
1+
#1036
0+
#1037
b111 /
1+
#1038
0+
#1039
0&
b1000 /
1+
#1040
0+
#1041
b1001 /
1+
#1042
0+
#1043
b1010 /
1+
#1044
0+
#1045
b1011 /
1+
#1046
0+
#1047
b1011 4
1&
b1100 /
1+
#1048
0+
#1049
b1101 /
1+
#1050
0+
#1051
b1110 /
1+
#1052
0+
#1053
b1111 /
1+
#1054
0+
#1055
0&
b0 /
1+
#1056
0+
0%
#1057
b1 /
1+
#1058
0+
#1059
b10 /
1+
#1060
0+
#1061
b11 /
1+
#1062
0+
#1063
b1111 4
1&
b100 /
1+
#1064
0+
#1065
b101 /
1+
#1066
0+
#1067
b110 /
1+
#1068
0+
#1069
b111 /
1+
