Tarea4/tester.v
module tester (
    input SCL,
    input SDA_OE,
    input SDA_OUT,
    input [15:0] RD_DATA,
    output reg CLK,
    output reg RESET,
    output reg SDA_IN,
    output reg [6:0] IC2_ADDR,
    output reg RNW,
    output reg START_STB,
    output reg [15:0] WR_DATA
);

//Creacion del reloj
always begin
    CLK = 1'b0; #0.5;
    CLK = 1'b1; #0.5;
end

// Pone todos los registros en cero
initial begin 
    RESET = 1'b0; #2; 
    #3;
    RESET = 1'b1; #2;
end


//Instrucciones para el generador de transacciones
initial begin

  
    //PRUEBA DE ESCRITURA
    SDA_IN = 1'b1; #2;
    SDA_IN = 0; #2;
    START_STB = 1'b0; #2;
    START_STB = 1'b1; #2;
    //START_STB = 1'b0; #2;
    IC2_ADDR = 7'b1010010;
    WR_DATA = 16'b1010_1000_0000_0001;
    RNW = 1'b1; #4; 
    START_STB = 0;
    #250;
    //WR_DATA = 16'b1000_0101_1010_0011; // segunda palabra
    #100; 


    //RUEBA DE LECTURA
    RESET = 0; #2;
    RESET = 1'b1; #2;
    //SDA_IN = 1; #1;
    START_STB = 1'b1; #2;
    //START_STB = 1'b0; #2;
    IC2_ADDR = 7'b1010010;
    RNW = 1'b0; #100;
    START_STB = 0;
    SDA_IN = 1; #10;
    SDA_IN = 0; #10;
    SDA_IN = 1; #10;
    SDA_IN = 1; #10;
    SDA_IN = 0; #10;
    SDA_IN = 1; #5;
    SDA_IN = 0; #5;
    SDA_IN = 1; #5;
    SDA_IN = 1; #5;
    SDA_IN = 0; #5;
    SDA_IN = 1; #5;
    SDA_IN = 0; #5;
    SDA_IN = 1; #5;
    SDA_IN = 1; #5;
    SDA_IN = 0; #5;
    //START_STB = 0;
    #100;
    //WR_DATA = 16'b1000_0101_1010_0011; // segunda palabra
    #60; #8;
    #8; 
    #100;




    $finish;

end

endmodule

Tarea3/contadores.v
// Contador de 2 bits para la senal de MCD

module contador2 (
input CLK,
input RESET,
output reg RESULT
);

always @(posedge CLK) begin
    if (~RESET || RESULT == 1'b1)
        RESULT <= 1'b0;
    else 
        RESULT <= 1'b1;


end
endmodule

module contador32 (
    input CLK,
    input RESET,
    input ENB,
    output reg [4:0] RESULT
);

always @(posedge CLK) begin
    if (~RESET || RESULT == 5'd31)  //5'd31 = 5'b11111
        RESULT <= 0;
    else 
        RESULT <= 1'b1;
    if (ENB && RESULT != 5'd31)
        RESULT <= RESULT + 1'b1;
    else
        RESULT <= 0;       
end


endmodule

Tarea4/IC2.v
`include "contadores.v"

module IC2 (
    input CLK,
    input RESET,
    input START_STB, //DICE CUANDO SE QUIERE INICIAR UNA TRANSACCION
    input RNW, // cuando =1 transaccion de lectura, =0 transaccion de escritura
    input [15:0] WR_DATA,
    input [6:0] IC2_ADDR,
    input SDA_IN, //como el MDIO_IN
    output SCL, //como el MDC, nada mas que esta vez al 25%
    output reg SDA_OE,
    output reg SDA_OUT, //como MDIO_OUT
    output reg [15:0] RD_DATA 
);


//aqui se guarda la el comportamiento al 50% de la senal de reloj
//reg MDC;
//Contador para generar un reloj con la mitad de frecuencia que es la mitad de CLK
contador2 mitad_frecuencia (
    .CLK(CLK),
    .RESET(RESET || ~(MDC === 1'bx)),
    .RESULT(MDC)
);

//25% de la frecuencia del reloj original 
contador2 frecuencia_al_25 (
    .CLK(MDC),
    .RESET(RESET || ~(SCL === 1'bx)),
    .RESULT(SCL)
);

reg [7:0] D;
reg [15:0] WR;


//Indica la iniciacion de un metodo de escritura o lectura
reg start_transmission;
reg start_data;


//Indica cuantos bits de datos se han transmitido a S_OUT
wire [4:0] contador;

//Al ser start_transmission la senal del ENB, solo se va a encender cuando start_transmission == 1
contador32 contador22 (
     .CLK(SCL),
     .RESET(RESET),
     .ENB(start_transmission),
     .RESULT(contador[4:0]) //para poder llegar al numero deseado en binario
);


//Inicio de transaccion y prueba de reset == 0, todos lo registros se vuelven cero.
always @(posedge CLK) begin
    if (RESET == 0) begin
        start_transmission <= 0;
        SDA_OUT = 0;
        SDA_OE = 0;
        RD_DATA[15:0] <= 0;
        start_data <= 0;
     end
     else if (start_data) begin
     end
end

always @(posedge SCL) begin
    if (START_STB) begin 
        start_data <= 1'b1;   
        SDA_OUT = 0;
        SDA_OE = 1'b1;
    end


     //si el contador es cero, y no se esta transmiitiendo nada la senal de mdio oe no se levantara.
     else if (contador == 5'd0 && ~start_transmission)
         SDA_OE <= 1'b0;

end

always @(start_data) begin
    D[0] <= RNW; 
    D[7:1] <= IC2_ADDR[6:0]; 
    WR[15:0] <= WR_DATA[15:0];
    //RD_DATA = 16'b1010_1011_0110_0011;
    start_transmission = 1'b1;
end




// modo de lectura o escritura
always @(posedge SCL) begin
     if (start_transmission) begin  
        start_data = 0;
        SDA_OUT <= D[7];  //Los datos guardados en D se desplazan a MDIO_OUT
        D = D << 1;
        if (contador > 5'd7 || contador == 5'b10100) begin //AKC
            SDA_OUT <= 1'b1;
            if (contador > 5'd8)
            SDA_OUT <= 0;

        end
     end
end
always @(posedge SCL) begin
    if (contador > 5'd9) begin
                case(RNW)        
                //ESCRITURA
                1'b1: begin 
                    SDA_OE <= 1'b1;   
                    SDA_OUT <= WR[15];
                    WR = WR << 1;
                    RD_DATA = 0;
                end
                //LECTURA
                1'b0:  begin
                    if (contador > 5'd9) begin
                    SDA_OE <= 1'b0;     
                    RD_DATA[0] <= SDA_IN;  
                    RD_DATA = RD_DATA << 1;
                    SDA_OUT = 0;
                end   
                end          
                default: begin SDA_OE <= 1'b0; end
                endcase
            end

        end

        //SDA_OE = 1'b1;      
        /*if (contador > 5'd8) begin
            case(RNW)        
                //ESCRITURA
                1'b1: begin 
                    if (contador < 5'd8) begin
                    SDA_OE <= 1'b1;   
                    SDA_OUT <= WR[15];
                    WR = WR << 1;
                    //RD_DATA = 0;
                    end
                end

                //LECTURA
                1'b0:  begin
                    SDA_OE <= 1'b0;     
                    RD_DATA[0] <= SDA_IN;  
                    RD_DATA = RD_DATA << 1;
                    SDA_OUT = 0;
                end             
                default: begin SDA_OE <= 1'b0; end
            endcase
        end*/
        //end
//end

endmodule

Tarea4/testbench.v
`include "IC2.v"
`include "tester.v"


//TESTBENCH
module testbench;
wire clk, rst, sda_in, start_stb, rnw, scl, sda_oe, sda_out;
wire[6:0] i2c_addr;
wire [15:0] wr_data;
wire [15:0] rd_data; 

//DUT
IC2 IC2_DUT (
    .CLK(clk),
    .RESET(rst),
    .SDA_IN(sda_in),
    .RNW(rnw),
    .START_STB(start_stb),
    .IC2_ADDR(i2c_addr[6:0]),
    .WR_DATA(wr_data[15:0]),
    .SCL(scl),
    .SDA_OE(sda_oe),
    .SDA_OUT(sda_out),
    .RD_DATA(rd_data[15:0])
);

//TESTER
tester TESTER (
    .CLK(clk),
    .RESET(rst),
    .SDA_IN(sda_in),
    .RNW(rnw),
    .START_STB(start_stb),
    .IC2_ADDR(i2c_addr[6:0]),
    .WR_DATA(wr_data[15:0]),
    .SCL(scl),
    .SDA_OE(sda_oe),
    .SDA_OUT(sda_out),
    .RD_DATA(rd_data)
);


/* para generar las ondas y
y visualizar en gtkwave
*/
initial begin
    $dumpfile("testbench.vcd");
    $dumpvars;
end


endmodule

Tarea4/testbench.vcd
$date
	Fri Oct 21 15:21:33 2022
$end
$version
	Icarus Verilog
$end
$timescale
	1s
$end
$scope module testbench $end
$var wire 16 ! wr_data [15:0] $end
$var wire 1 " start_stb $end
$var wire 1 # sda_out $end
$var wire 1 $ sda_oe $end
$var wire 1 % sda_in $end
$var wire 1 & scl $end
$var wire 1 ' rst $end
$var wire 1 ( rnw $end
$var wire 16 ) rd_data [15:0] $end
$var wire 7 * i2c_addr [6:0] $end
$var wire 1 + clk $end
$scope module IC2_DUT $end
$var wire 5 , contador [4:0] $end
$var wire 16 - WR_DATA [15:0] $end
$var wire 1 " START_STB $end
$var wire 1 % SDA_IN $end
$var wire 1 & SCL $end
$var wire 1 ( RNW $end
$var wire 1 ' RESET $end
$var wire 1 . MDC $end
$var wire 7 / IC2_ADDR [6:0] $end
$var wire 1 + CLK $end
$var reg 8 0 D [7:0] $end
$var reg 16 1 RD_DATA [15:0] $end
$var reg 1 $ SDA_OE $end
$var reg 1 # SDA_OUT $end
$var reg 16 2 WR [15:0] $end
$var reg 1 3 start_data $end
$var reg 1 4 start_transmission $end
$scope module contador22 $end
$var wire 1 4 ENB $end
$var wire 1 ' RESET $end
$var wire 1 & CLK $end
$var reg 5 5 RESULT [4:0] $end
$upscope $end
$scope module frecuencia_al_25 $end
$var wire 1 6 RESET $end
$var wire 1 . CLK $end
$var reg 1 & RESULT $end
$upscope $end
$scope module mitad_frecuencia $end
$var wire 1 7 RESET $end
$var wire 1 + CLK $end
$var reg 1 . RESULT $end
$upscope $end
$upscope $end
$scope module TESTER $end
$var wire 16 8 RD_DATA [15:0] $end
$var wire 1 & SCL $end
$var wire 1 $ SDA_OE $end
$var wire 1 # SDA_OUT $end
$var reg 1 + CLK $end
$var reg 7 9 IC2_ADDR [6:0] $end
$var reg 1 ' RESET $end
$var reg 1 ( RNW $end
$var reg 1 % SDA_IN $end
$var reg 1 " START_STB $end
$var reg 16 : WR_DATA [15:0] $end
$upscope $end
$upscope $end
$enddefinitions $end
#0
$dumpvars
bx :
bx 9
bx 8
07
06
bx 5
x4
x3
bx 2
bx 1
bx 0
bx /
x.
bx -
bx ,
0+
bx *
bx )
x(
0'
x&
1%
x$
x#
x"
bx !
$end
#1
17
0.
03
b0 )
b0 1
b0 8
14
0$
0#
1+
#2
0+
0%
#3
16
0&
04
1.
1+
#4
0+
0"
#5
0.
1+
1'
#6
0+
1"
#7
14
b0 ,
b0 5
13
1$
1&
1.
1+
#8
0+
1(
b1010100000000001 !
b1010100000000001 -
b1010100000000001 :
b1010010 *
b1010010 /
b1010010 9
#9
0.
1+
#10
0+
#11
0&
1.
1+
#12
0+
0"
#13
0.
1+
#14
0+
#15
b1010100000000001 2
x#
b1 ,
b1 5
b10100101 0
03
1&
1.
1+
#16
0+
#17
0.
1+
#18
0+
#19
0&
1.
1+
#20
0+
#21
0.
1+
#22
0+
#23
b10 ,
b10 5
1#
b1001010 0
1&
1.
1+
#24
0+
#25
0.
1+
#26
0+
#27
0&
1.
1+
#28
0+
#29
0.
1+
#30
0+
#31
0#
b11 ,
b11 5
b10010100 0
1&
1.
1+
#32
0+
#33
0.
1+
#34
0+
#35
0&
1.
1+
#36
0+
#37
0.
1+
#38
0+
#39
b100 ,
b100 5
1#
b101000 0
1&
1.
1+
#40
0+
#41
0.
1+
#42
0+
#43
0&
1.
1+
#44
0+
#45
0.
1+
#46
0+
#47
0#
b101 ,
b101 5
b1010000 0
1&
1.
1+
#48
0+
#49
0.
1+
#50
0+
#51
0&
1.
1+
#52
0+
#53
0.
1+
#54
0+
#55
b110 ,
b110 5
b10100000 0
1&
1.
1+
#56
0+
#57
0.
1+
#58
0+
#59
0&
1.
1+
#60
0+
#61
0.
1+
#62
0+
#63
1#
b111 ,
b111 5
b1000000 0
1&
1.
1+
#64
0+
#65
0.
1+
#66
0+
#67
0&
1.
1+
#68
0+
#69
0.
1+
#70
0+
#71
b1000 ,
b1000 5
0#
b10000000 0
1&
1.
1+
#72
0+
#73
0.
1+
#74
0+
#75
0&
1.
1+
#76
0+
#77
0.
1+
#78
0+
#79
1#
b1001 ,
b1001 5
b0 0
1&
1.
1+
#80
0+
#81
0.
1+
#82
0+
#83
0&
1.
1+
#84
0+
#85
0.
1+
#86
0+
#87
b1010 ,
b1010 5
0#
1&
1.
1+
#88
0+
#89
0.
1+
#90
0+
#91
0&
1.
1+
#92
0+
#93
0.
1+
#94
0+
#95
1#
b1011 ,
b1011 5
b101000000000010 2
1&
1.
1+
#96
0+
#97
0.
1+
#98
0+
#99
0&
1.
1+
#100
0+
#101
0.
1+
#102
0+
#103
b1100 ,
b1100 5
0#
b1010000000000100 2
1&
1.
1+
#104
0+
#105
0.
1+
#106
0+
#107
0&
1.
1+
#108
0+
#109
0.
1+
#110
0+
#111
1#
b1101 ,
b1101 5
b100000000001000 2
1&
1.
1+
#112
0+
#113
0.
1+
#114
0+
#115
0&
1.
1+
#116
0+
#117
0.
1+
#118
0+
#119
b1110 ,
b1110 5
0#
b1000000000010000 2
1&
1.
1+
#120
0+
#121
0.
1+
#122
0+
#123
0&
1.
1+
#124
0+
#125
0.
1+
#126
0+
#127
1#
b1111 ,
b1111 5
b100000 2
1&
1.
1+
#128
0+
#129
0.
1+
#130
0+
#131
0&
1.
1+
#132
0+
#133
0.
1+
#134
0+
#135
b10000 ,
b10000 5
0#
b1000000 2
1&
1.
1+
#136
0+
#137
0.
1+
#138
0+
#139
0&
1.
1+
#140
0+
#141
0.
1+
#142
0+
#143
0#
b10001 ,
b10001 5
b10000000 2
1&
1.
1+
#144
0+
#145
0.
1+
#146
0+
#147
0&
1.
1+
#148
0+
#149
0.
1+
#150
0+
#151
b10010 ,
b10010 5
0#
b100000000 2
1&
1.
1+
#152
0+
#153
0.
1+
#154
0+
#155
0&
1.
1+
#156
0+
#157
0.
1+
#158
0+
#159
0#
b10011 ,
b10011 5
b1000000000 2
1&
1.
1+
#160
0+
#161
0.
1+
#162
0+
#163
0&
1.
1+
#164
0+
#165
0.
1+
#166
0+
#167
b10100 ,
b10100 5
0#
b10000000000 2
1&
1.
1+
#168
0+
#169
0.
1+
#170
0+
#171
0&
1.
1+
#172
0+
#173
0.
1+
#174
0+
#175
0#
b10101 ,
b10101 5
b100000000000 2
1&
1.
1+
#176
0+
#177
0.
1+
#178
0+
#179
0&
1.
1+
#180
0+
#181
0.
1+
#182
0+
#183
b10110 ,
b10110 5
0#
b1000000000000 2
1&
1.
1+
#184
0+
#185
0.
1+
#186
0+
#187
0&
1.
1+
#188
0+
#189
0.
1+
#190
0+
#191
0#
b10111 ,
b10111 5
b10000000000000 2
1&
1.
1+
#192
0+
#193
0.
1+
#194
0+
#195
0&
1.
1+
#196
0+
#197
0.
1+
#198
0+
#199
b11000 ,
b11000 5
0#
b100000000000000 2
1&
1.
1+
#200
0+
#201
0.
1+
#202
0+
#203
0&
1.
1+
#204
0+
#205
0.
1+
#206
0+
#207
0#
b11001 ,
b11001 5
b1000000000000000 2
1&
1.
1+
#208
0+
#209
0.
1+
#210
0+
#211
0&
1.
1+
#212
0+
#213
0.
1+
#214
0+
#215
b11010 ,
b11010 5
0#
b0 2
1&
1.
1+
#216
0+
#217
0.
1+
#218
0+
#219
0&
1.
1+
#220
0+
#221
0.
1+
#222
0+
#223
0#
b11011 ,
b11011 5
1&
1.
1+
#224
0+
#225
0.
1+
#226
0+
#227
0&
1.
1+
#228
0+
#229
0.
1+
#230
0+
#231
b11100 ,
b11100 5
0#
1&
1.
1+
#232
0+
#233
0.
1+
#234
0+
#235
0&
1.
1+
#236
0+
#237
0.
1+
#238
0+
#239
0#
b11101 ,
b11101 5
1&
1.
1+
#240
0+
#241
0.
1+
#242
0+
#243
0&
1.
1+
#244
0+
#245
0.
1+
#246
0+
#247
b11110 ,
b11110 5
0#
1&
1.
1+
#248
0+
#249
0.
1+
#250
0+
#251
0&
1.
1+
#252
0+
#253
0.
1+
#254
0+
#255
0#
b11111 ,
b11111 5
1&
1.
1+
#256
0+
#257
0.
1+
#258
0+
#259
0&
1.
1+
#260
0+
#261
0.
1+
#262
0+
#263
b0 ,
b0 5
0#
1&
1.
1+
#264
0+
#265
0.
1+
#266
0+
#267
0&
1.
1+
#268
0+
#269
0.
1+
#270
0+
#271
b1 ,
b1 5
1&
1.
1+
#272
0+
#273
0.
1+
#274
0+
#275
0&
1.
1+
#276
0+
#277
0.
1+
#278
0+
#279
b10 ,
b10 5
1&
1.
1+
#280
0+
#281
0.
1+
#282
0+
#283
0&
1.
1+
#284
0+
#285
0.
1+
#286
0+
#287
b11 ,
b11 5
1&
1.
1+
#288
0+
#289
0.
1+
#290
0+
#291
0&
1.
1+
#292
0+
#293
0.
1+
#294
0+
#295
b100 ,
b100 5
1&
1.
1+
#296
0+
#297
0.
1+
#298
0+
#299
0&
1.
1+
#300
0+
#301
0.
1+
#302
0+
#303
b101 ,
b101 5
1&
1.
1+
#304
0+
#305
0.
1+
#306
0+
#307
0&
1.
1+
#308
0+
#309
0.
1+
#310
0+
#311
b110 ,
b110 5
1&
1.
1+
#312
0+
#313
0.
1+
#314
0+
#315
0&
1.
1+
#316
0+
#317
0.
1+
#318
0+
#319
b111 ,
b111 5
1&
1.
1+
#320
0+
#321
0.
1+
#322
0+
#323
0&
1.
1+
#324
0+
#325
0.
1+
#326
0+
#327
b1000 ,
b1000 5
1&
1.
1+
#328
0+
#329
0.
1+
#330
0+
#331
0&
1.
1+
#332
0+
#333
0.
1+
#334
0+
#335
1#
b1001 ,
b1001 5
1&
1.
1+
#336
0+
#337
0.
1+
#338
0+
#339
0&
1.
1+
#340
0+
#341
0.
1+
#342
0+
#343
b1010 ,
b1010 5
0#
1&
1.
1+
#344
0+
#345
0.
1+
#346
0+
#347
0&
1.
1+
#348
0+
#349
0.
1+
#350
0+
#351
0#
b1011 ,
b1011 5
1&
1.
1+
#352
0+
#353
0.
1+
#354
0+
#355
0&
1.
1+
#356
0+
#357
0.
1+
#358
0+
#359
b1100 ,
b1100 5
0#
1&
1.
1+
#360
0+
#361
0.
1+
#362
0+
0'
#363
0&
04
1.
0$
1+
#364
0+
1'
#365
0.
1+
#366
0+
1"
#367
b1010100000000001 2
b10100101 0
14
13
b0 ,
b0 5
1$
1&
1.
1+
#368
0+
0(
#369
0.
1+
#370
0+
#371
0&
1.
1+
#372
0+
#373
0.
1+
#374
0+
#375
b1 ,
b1 5
1#
b10100100 0
13
1&
1.
1+
#376
0+
#377
0.
1+
#378
0+
#379
0&
1.
1+
#380
0+
#381
0.
1+
#382
0+
#383
b10 ,
b10 5
b10100100 0
13
1#
1&
1.
1+
#384
0+
#385
0.
1+
#386
0+
#387
0&
1.
1+
#388
0+
#389
0.
1+
#390
0+
#391
b11 ,
b11 5
1#
b10100100 0
13
1&
1.
1+
#392
0+
#393
0.
1+
#394
0+
#395
0&
1.
1+
#396
0+
#397
0.
1+
#398
0+
#399
b100 ,
b100 5
b10100100 0
13
1#
1&
1.
1+
#400
0+
#401
0.
1+
#402
0+
#403
0&
1.
1+
#404
0+
#405
0.
1+
#406
0+
#407
b101 ,
b101 5
1#
b10100100 0
13
1&
1.
1+
#408
0+
#409
0.
1+
#410
0+
#411
0&
1.
1+
#412
0+
#413
0.
1+
#414
0+
#415
b110 ,
b110 5
b10100100 0
13
1#
1&
1.
1+
#416
0+
#417
0.
1+
#418
0+
#419
0&
1.
1+
#420
0+
#421
0.
1+
#422
0+
#423
b111 ,
b111 5
1#
b10100100 0
13
1&
1.
1+
#424
0+
#425
0.
1+
#426
0+
#427
0&
1.
1+
#428
0+
#429
0.
1+
#430
0+
#431
b1000 ,
b1000 5
b10100100 0
13
1#
1&
1.
1+
#432
0+
#433
0.
1+
#434
0+
#435
0&
1.
1+
#436
0+
#437
0.
1+
#438
0+
#439
b1001 ,
b1001 5
1#
b10100100 0
13
1&
1.
1+
#440
0+
#441
0.
1+
#442
0+
#443
0&
1.
1+
#444
0+
#445
0.
1+
#446
0+
#447
b1010 ,
b1010 5
b10100100 0
13
0#
1&
1.
1+
#448
0+
#449
0.
1+
#450
0+
#451
0&
1.
1+
#452
0+
#453
0.
1+
#454
0+
#455
b1011 ,
b1011 5
0#
0$
b10100100 0
13
1&
1.
1+
#456
0+
#457
0.
1+
#458
0+
#459
0&
1.
1+
#460
0+
#461
0.
1+
#462
0+
#463
0#
b1100 ,
b1100 5
b10100100 0
13
0$
1&
1.
1+
#464
0+
#465
0.
1+
#466
0+
#467
0&
1.
1+
#468
0+
1%
0"
#469
0.
1+
#470
0+
#471
b1101 ,
b1101 5
0#
b1 )
b1 1
b1 8
b10100100 0
03
1&
1.
1+
#472
0+
#473
0.
1+
#474
0+
#475
0&
1.
1+
#476
0+
#477
0.
1+
#478
0+
0%
#479
0#
b1110 ,
b1110 5
b10 )
b10 1
b10 8
b1001000 0
1&
1.
1+
#480
0+
#481
0.
1+
#482
0+
#483
0&
1.
1+
#484
0+
#485
0.
1+
#486
0+
#487
b1111 ,
b1111 5
0#
b10010000 0
b100 )
b100 1
b100 8
1&
1.
1+
#488
0+
1%
#489
0.
1+
#490
0+
#491
0&
1.
1+
#492
0+
#493
0.
1+
#494
0+
#495
0#
b10000 ,
b10000 5
b1001 )
b1001 1
b1001 8
b100000 0
1&
1.
1+
#496
0+
#497
0.
1+
#498
0+
#499
0&
1.
1+
#500
0+
#501
0.
1+
#502
0+
#503
b10001 ,
b10001 5
0#
b1000000 0
b10011 )
b10011 1
b10011 8
1&
1.
1+
#504
0+
#505
0.
1+
#506
0+
#507
0&
1.
1+
#508
0+
0%
#509
0.
1+
#510
0+
#511
0#
b10010 ,
b10010 5
b100110 )
b100110 1
b100110 8
b10000000 0
1&
1.
1+
#512
0+
#513
0.
1+
#514
0+
#515
0&
1.
1+
#516
0+
#517
0.
1+
#518
0+
1%
#519
b10011 ,
b10011 5
0#
b0 0
b1001101 )
b1001101 1
b1001101 8
1&
1.
1+
#520
0+
#521
0.
1+
#522
0+
#523
0&
1.
1+
0%
#524
0+
#525
0.
1+
#526
0+
#527
0#
b10100 ,
b10100 5
b10011010 )
b10011010 1
b10011010 8
1&
1.
1+
#528
0+
1%
#529
0.
1+
#530
0+
#531
0&
1.
1+
#532
0+
#533
0.
1+
#534
0+
#535
b10101 ,
b10101 5
0#
b100110101 )
b100110101 1
b100110101 8
1&
1.
1+
#536
0+
#537
0.
1+
#538
0+
0%
#539
0&
1.
1+
#540
0+
#541
0.
1+
#542
0+
#543
0#
b10110 ,
b10110 5
b1001101011 )
b1001101011 1
b1001101011 8
1&
1.
1+
1%
#544
0+
#545
0.
1+
#546
0+
#547
0&
1.
1+
#548
0+
0%
#549
0.
1+
#550
0+
#551
b10111 ,
b10111 5
0#
b10011010110 )
b10011010110 1
b10011010110 8
1&
1.
1+
#552
0+
#553
0.
1+
1%
#554
0+
#555
0&
1.
1+
#556
0+
#557
0.
1+
#558
0+
#559
0#
b11000 ,
b11000 5
b100110101101 )
b100110101101 1
b100110101101 8
1&
1.
1+
#560
0+
#561
0.
1+
#562
0+
#563
0&
1.
1+
0%
#564
0+
#565
0.
1+
#566
0+
#567
b11001 ,
b11001 5
0#
b1001101011010 )
b1001101011010 1
b1001101011010 8
1&
1.
1+
#568
0+
#569
0.
1+
#570
0+
#571
0&
1.
1+
#572
0+
#573
0.
1+
#574
0+
#575
0#
b11010 ,
b11010 5
b10011010110100 )
b10011010110100 1
b10011010110100 8
1&
1.
1+
#576
0+
#577
0.
1+
#578
0+
#579
0&
1.
1+
#580
0+
#581
0.
1+
#582
0+
#583
b11011 ,
b11011 5
0#
b100110101101000 )
b100110101101000 1
b100110101101000 8
1&
1.
1+
#584
0+
#585
0.
1+
#586
0+
#587
0&
1.
1+
#588
0+
#589
0.
1+
#590
0+
#591
0#
b11100 ,
b11100 5
b1001101011010000 )
b1001101011010000 1
b1001101011010000 8
1&
1.
1+
#592
0+
#593
0.
1+
#594
0+
#595
0&
1.
1+
#596
0+
#597
0.
1+
#598
0+
#599
b11101 ,
b11101 5
0#
b11010110100000 )
b11010110100000 1
b11010110100000 8
1&
1.
1+
#600
0+
#601
0.
1+
#602
0+
#603
0&
1.
1+
#604
0+
#605
0.
1+
#606
0+
#607
0#
b11110 ,
b11110 5
b110101101000000 )
b110101101000000 1
b110101101000000 8
1&
1.
1+
#608
0+
#609
0.
1+
#610
0+
#611
0&
1.
1+
#612
0+
#613
0.
1+
#614
0+
#615
b11111 ,
b11111 5
0#
b1101011010000000 )
b1101011010000000 1
b1101011010000000 8
1&
1.
1+
#616
0+
#617
0.
1+
#618
0+
#619
0&
1.
1+
#620
0+
#621
0.
1+
#622
0+
#623
0#
b0 ,
b0 5
b1010110100000000 )
b1010110100000000 1
b1010110100000000 8
1&
1.
1+
#624
0+
#625
0.
1+
#626
0+
#627
0&
1.
1+
#628
0+
#629
0.
1+
#630
0+
#631
b1 ,
b1 5
1&
1.
1+
#632
0+
#633
0.
1+
#634
0+
#635
0&
1.
1+
#636
0+
#637
0.
1+
#638
0+
#639
b10 ,
b10 5
1&
1.
1+
#640
0+
#641
0.
1+
#642
0+
#643
0&
1.
1+
#644
0+
#645
0.
1+
#646
0+
#647
b11 ,
b11 5
1&
1.
1+
#648
0+
#649
0.
1+
#650
0+
#651
0&
1.
1+
#652
0+
#653
0.
1+
#654
0+
#655
b100 ,
b100 5
1&
1.
1+
#656
0+
#657
0.
1+
#658
0+
#659
0&
1.
1+
#660
0+
#661
0.
1+
#662
0+
#663
b101 ,
b101 5
1&
1.
1+
#664
0+
#665
0.
1+
#666
0+
#667
0&
1.
1+
#668
0+
#669
0.
1+
#670
0+
#671
b110 ,
b110 5
1&
1.
1+
#672
0+
#673
0.
1+
#674
0+
#675
0&
1.
1+
#676
0+
#677
0.
1+
#678
0+
#679
b111 ,
b111 5
1&
1.
1+
#680
0+
#681
0.
1+
#682
0+
#683
0&
1.
1+
#684
0+
#685
0.
1+
#686
0+
#687
b1000 ,
b1000 5
1&
1.
1+
#688
0+
#689
0.
1+
#690
0+
#691
0&
1.
1+
#692
0+
#693
0.
1+
#694
0+
#695
b1001 ,
b1001 5
1#
1&
1.
1+
#696
0+
#697
0.
1+
#698
0+
#699
0&
1.
1+
#700
0+
#701
0.
1+
#702
0+
#703
0#
b1010 ,
b1010 5
1&
1.
1+
#704
0+
#705
0.
1+
#706
0+
#707
0&
1.
1+
#708
0+
#709
0.
1+
#710
0+
#711
b1011 ,
b1011 5
0#
b101101000000000 )
b101101000000000 1
b101101000000000 8
1&
1.
1+
#712
0+
#713
0.
1+
#714
0+
#715
0&
1.
1+
#716
0+
#717
0.
1+
#718
0+
#719
0#
b1100 ,
b1100 5
b1011010000000000 )
b1011010000000000 1
b1011010000000000 8
1&
1.
1+
#720
0+
#721
0.
1+
#722
0+
#723
0&
1.
1+
#724
0+
#725
0.
1+
#726
0+
#727
b1101 ,
b1101 5
0#
b110100000000000 )
b110100000000000 1
b110100000000000 8
1&
1.
1+
#728
0+
#729
0.
1+
#730
0+
#731
0&
1.
1+
#732
0+
#733
0.
1+
#734
0+
#735
0#
b1110 ,
b1110 5
b1101000000000000 )
b1101000000000000 1
b1101000000000000 8
1&
1.
1+
#736
0+
#737
0.
1+
#738
0+
#739
0&
1.
1+
#740
0+
#741
0.
1+
#742
0+
#743
b1111 ,
b1111 5
0#
b1010000000000000 )
b1010000000000000 1
b1010000000000000 8
1&
1.
1+
#744
0+
#745
0.
1+
#746
0+
#747
0&
1.
1+
#748
0+
#749
0.
1+
#750
0+
#751
0#
b10000 ,
b10000 5
b100000000000000 )
b100000000000000 1
b100000000000000 8
1&
1.
1+
#752
0+
#753
0.
1+
#754
0+
#755
0&
1.
1+
#756
0+
#757
0.
1+
#758
0+
#759
b10001 ,
b10001 5
0#
b1000000000000000 )
b1000000000000000 1
b1000000000000000 8
1&
1.
1+
#760
0+
#761
0.
1+
#762
0+
#763
0&
1.
1+
#764
0+
#765
0.
1+
#766
0+
#767
0#
b10010 ,
b10010 5
b0 )
b0 1
b0 8
1&
1.
1+
#768
0+
#769
0.
1+
#770
0+
#771
0&
1.
1+
#772
0+
#773
0.
1+
#774
0+
#775
b10011 ,
b10011 5
0#
1&
1.
1+
#776
0+
#777
0.
1+
#778
0+
#779
0&
1.
1+
#780
0+
#781
0.
1+
#782
0+
#783
0#
b10100 ,
b10100 5
1&
1.
1+
#784
0+
#785
0.
1+
#786
0+
#787
0&
1.
1+
#788
0+
#789
0.
1+
#790
0+
#791
b10101 ,
b10101 5
0#
1&
1.
1+
#792
0+
#793
0.
1+
#794
0+
#795
0&
1.
1+
#796
0+
#797
0.
1+
#798
0+
#799
0#
b10110 ,
b10110 5
1&
1.
1+
#800
0+
#801
0.
1+
#802
0+
#803
0&
1.
1+
#804
0+
#805
0.
1+
#806
0+
#807
b10111 ,
b10111 5
0#
1&
1.
1+
#808
0+
#809
0.
1+
#810
0+
#811
0&
1.
1+
#812
0+
#813
0.
1+
#814
0+
#815
0#
b11000 ,
b11000 5
1&
1.
1+
#816
0+
#817
0.
1+
#818
0+
#819
0&
1.
1+
#820
0+
#821
0.
1+
#822
0+
#823
b11001 ,
b11001 5
0#
1&
1.
1+
#824
0+
#825
0.
1+
#826
0+
#827
0&
1.
1+
#828
0+
#829
0.
1+
#830
0+
#831
0#
b11010 ,
b11010 5
1&
1.
1+
#832
0+
#833
0.
1+
#834
0+
#835
0&
1.
1+
#836
0+
#837
0.
1+
#838
0+
#839
b11011 ,
b11011 5
0#
1&
1.
1+
